Workbook

Sheet Fleet growth and revenue
A1: Fleet growth and revenue
A2: Detour — Revenue and van economics · Main Scenario
A4: Variable / dimension | B4: 2026-10 | C4: 2026-11 | D4: 2026-12 | E4: 2027-01 | F4: 2027-02 | G4: 2027-03 | H4: 2027-04 | I4: 2027-05 | J4: 2027-06 | K4: 2027-07 | L4: 2027-08 | M4: 2027-09 | N4: 2027-10 | O4: 2027-11 | P4: 2027-12 | Q4: 2028-01 | R4: 2028-02 | S4: 2028-03 | T4: 2028-04 | U4: 2028-05 | V4: 2028-06 | W4: 2028-07 | X4: 2028-08 | Y4: 2028-09
A5: Plan month | B5: =DATEDIF('Model inputs'!AA23,DATE(2026,10,1),"M")+1 -> 1 | C5: =DATEDIF('Model inputs'!AA23,DATE(2026,11,1),"M")+1 -> 2 | D5: =DATEDIF('Model inputs'!AA23,DATE(2026,12,1),"M")+1 -> 3 | E5: =DATEDIF('Model inputs'!AA23,DATE(2027,1,1),"M")+1 -> 4 | F5: =DATEDIF('Model inputs'!AA23,DATE(2027,2,1),"M")+1 -> 5 | G5: =DATEDIF('Model inputs'!AA23,DATE(2027,3,1),"M")+1 -> 6 | H5: =DATEDIF('Model inputs'!AA23,DATE(2027,4,1),"M")+1 -> 7 | I5: =DATEDIF('Model inputs'!AA23,DATE(2027,5,1),"M")+1 -> 8 | J5: =DATEDIF('Model inputs'!AA23,DATE(2027,6,1),"M")+1 -> 9 | K5: =DATEDIF('Model inputs'!AA23,DATE(2027,7,1),"M")+1 -> 10 | L5: =DATEDIF('Model inputs'!AA23,DATE(2027,8,1),"M")+1 -> 11 | M5: =DATEDIF('Model inputs'!AA23,DATE(2027,9,1),"M")+1 -> 12 | N5: =DATEDIF('Model inputs'!AA23,DATE(2027,10,1),"M")+1 -> 13 | O5: =DATEDIF('Model inputs'!AA23,DATE(2027,11,1),"M")+1 -> 14 | P5: =DATEDIF('Model inputs'!AA23,DATE(2027,12,1),"M")+1 -> 15 | Q5: =DATEDIF('Model inputs'!AA23,DATE(2028,1,1),"M")+1 -> 16 | R5: =DATEDIF('Model inputs'!AA23,DATE(2028,2,1),"M")+1 -> 17 | S5: =DATEDIF('Model inputs'!AA23,DATE(2028,3,1),"M")+1 -> 18 | T5: =DATEDIF('Model inputs'!AA23,DATE(2028,4,1),"M")+1 -> 19 | U5: =DATEDIF('Model inputs'!AA23,DATE(2028,5,1),"M")+1 -> 20 | V5: =DATEDIF('Model inputs'!AA23,DATE(2028,6,1),"M")+1 -> 21 | W5: =DATEDIF('Model inputs'!AA23,DATE(2028,7,1),"M")+1 -> 22 | X5: =DATEDIF('Model inputs'!AA23,DATE(2028,8,1),"M")+1 -> 23 | Y5: =DATEDIF('Model inputs'!AA23,DATE(2028,9,1),"M")+1 -> 24
A6: Active fleet target | B6: =IF(IF(IF(ISERROR('Fleet growth and revenue'!B5<'Model inputs'!AA33),'Fleet growth and revenue'!B5<'Model inputs'!AA33,IF(OR('Fleet growth and revenue'!B5="",'Model inputs'!AA33=""),"",'Fleet growth and revenue'!B5<'Model inputs'!AA33))="",FALSE,IF(ISERROR('Fleet growth and revenue'!B5<'Model inputs'!AA33),'Fleet growth and revenue'!B5<'Model inputs'!AA33,IF(OR('Fleet growth and revenue'!B5="",'Model inputs'!AA33=""),"",'Fleet growth and revenue'!B5<'Model inputs'!AA33))),0,ROUND('Model inputs'!AA32+('Model inputs'!AA31-'Model inputs'!AA32)*('Fleet growth and revenue'!B5-'Model inputs'!AA33)/('Model inputs'!AA34-'Model inputs'!AA33),0)) -> 0 | C6: =IF(IF(IF(ISERROR('Fleet growth and revenue'!C5<'Model inputs'!AA33),'Fleet growth and revenue'!C5<'Model inputs'!AA33,IF(OR('Fleet growth and revenue'!C5="",'Model inputs'!AA33=""),"",'Fleet growth and revenue'!C5<'Model inputs'!AA33))="",FALSE,IF(ISERROR('Fleet growth and revenue'!C5<'Model inputs'!AA33),'Fleet growth and revenue'!C5<'Model inputs'!AA33,IF(OR('Fleet growth and revenue'!C5="",'Model inputs'!AA33=""),"",'Fleet growth and revenue'!C5<'Model inputs'!AA33))),0,ROUND('Model inputs'!AA32+('Model inputs'!AA31-'Model inputs'!AA32)*('Fleet growth and revenue'!C5-'Model inputs'!AA33)/('Model inputs'!AA34-'Model inputs'!AA33),0)) -> 0 | D6: =IF(IF(IF(ISERROR('Fleet growth and revenue'!D5<'Model inputs'!AA33),'Fleet growth and revenue'!D5<'Model inputs'!AA33,IF(OR('Fleet growth and revenue'!D5="",'Model inputs'!AA33=""),"",'Fleet growth and revenue'!D5<'Model inputs'!AA33))="",FALSE,IF(ISERROR('Fleet growth and revenue'!D5<'Model inputs'!AA33),'Fleet growth and revenue'!D5<'Model inputs'!AA33,IF(OR('Fleet growth and revenue'!D5="",'Model inputs'!AA33=""),"",'Fleet growth and revenue'!D5<'Model inputs'!AA33))),0,ROUND('Model inputs'!AA32+('Model inputs'!AA31-'Model inputs'!AA32)*('Fleet growth and revenue'!D5-'Model inputs'!AA33)/('Model inputs'!AA34-'Model inputs'!AA33),0)) -> 3 | E6: =IF(IF(IF(ISERROR('Fleet growth and revenue'!E5<'Model inputs'!AA33),'Fleet growth and revenue'!E5<'Model inputs'!AA33,IF(OR('Fleet growth and revenue'!E5="",'Model inputs'!AA33=""),"",'Fleet growth and revenue'!E5<'Model inputs'!AA33))="",FALSE,IF(ISERROR('Fleet growth and revenue'!E5<'Model inputs'!AA33),'Fleet growth and revenue'!E5<'Model inputs'!AA33,IF(OR('Fleet growth and revenue'!E5="",'Model inputs'!AA33=""),"",'Fleet growth and revenue'!E5<'Model inputs'!AA33))),0,ROUND('Model inputs'!AA32+('Model inputs'!AA31-'Model inputs'!AA32)*('Fleet growth and revenue'!E5-'Model inputs'!AA33)/('Model inputs'!AA34-'Model inputs'!AA33),0)) -> 6 | F6: =IF(IF(IF(ISERROR('Fleet growth and revenue'!F5<'Model inputs'!AA33),'Fleet growth and revenue'!F5<'Model inputs'!AA33,IF(OR('Fleet growth and revenue'!F5="",'Model inputs'!AA33=""),"",'Fleet growth and revenue'!F5<'Model inputs'!AA33))="",FALSE,IF(ISERROR('Fleet growth and revenue'!F5<'Model inputs'!AA33),'Fleet growth and revenue'!F5<'Model inputs'!AA33,IF(OR('Fleet growth and revenue'!F5="",'Model inputs'!AA33=""),"",'Fleet growth and revenue'!F5<'Model inputs'!AA33))),0,ROUND('Model inputs'!AA32+('Model inputs'!AA31-'Model inputs'!AA32)*('Fleet growth and revenue'!F5-'Model inputs'!AA33)/('Model inputs'!AA34-'Model inputs'!AA33),0)) -> 8 | G6: =IF(IF(IF(ISERROR('Fleet growth and revenue'!G5<'Model inputs'!AA33),'Fleet growth and revenue'!G5<'Model inputs'!AA33,IF(OR('Fleet growth and revenue'!G5="",'Model inputs'!AA33=""),"",'Fleet growth and revenue'!G5<'Model inputs'!AA33))="",FALSE,IF(ISERROR('Fleet growth and revenue'!G5<'Model inputs'!AA33),'Fleet growth and revenue'!G5<'Model inputs'!AA33,IF(OR('Fleet growth and revenue'!G5="",'Model inputs'!AA33=""),"",'Fleet growth and revenue'!G5<'Model inputs'!AA33))),0,ROUND('Model inputs'!AA32+('Model inputs'!AA31-'Model inputs'!AA32)*('Fleet growth and revenue'!G5-'Model inputs'!AA33)/('Model inputs'!AA34-'Model inputs'!AA33),0)) -> 11 | H6: =IF(IF(IF(ISERROR('Fleet growth and revenue'!H5<'Model inputs'!AA33),'Fleet growth and revenue'!H5<'Model inputs'!AA33,IF(OR('Fleet growth and revenue'!H5="",'Model inputs'!AA33=""),"",'Fleet growth and revenue'!H5<'Model inputs'!AA33))="",FALSE,IF(ISERROR('Fleet growth and revenue'!H5<'Model inputs'!AA33),'Fleet growth and revenue'!H5<'Model inputs'!AA33,IF(OR('Fleet growth and revenue'!H5="",'Model inputs'!AA33=""),"",'Fleet growth and revenue'!H5<'Model inputs'!AA33))),0,ROUND('Model inputs'!AA32+('Model inputs'!AA31-'Model inputs'!AA32)*('Fleet growth and revenue'!H5-'Model inputs'!AA33)/('Model inputs'!AA34-'Model inputs'!AA33),0)) -> 14 | I6: =IF(IF(IF(ISERROR('Fleet growth and revenue'!I5<'Model inputs'!AA33),'Fleet growth and revenue'!I5<'Model inputs'!AA33,IF(OR('Fleet growth and revenue'!I5="",'Model inputs'!AA33=""),"",'Fleet growth and revenue'!I5<'Model inputs'!AA33))="",FALSE,IF(ISERROR('Fleet growth and revenue'!I5<'Model inputs'!AA33),'Fleet growth and revenue'!I5<'Model inputs'!AA33,IF(OR('Fleet growth and revenue'!I5="",'Model inputs'!AA33=""),"",'Fleet growth and revenue'!I5<'Model inputs'!AA33))),0,ROUND('Model inputs'!AA32+('Model inputs'!AA31-'Model inputs'!AA32)*('Fleet growth and revenue'!I5-'Model inputs'!AA33)/('Model inputs'!AA34-'Model inputs'!AA33),0)) -> 17 | J6: =IF(IF(IF(ISERROR('Fleet growth and revenue'!J5<'Model inputs'!AA33),'Fleet growth and revenue'!J5<'Model inputs'!AA33,IF(OR('Fleet growth and revenue'!J5="",'Model inputs'!AA33=""),"",'Fleet growth and revenue'!J5<'Model inputs'!AA33))="",FALSE,IF(ISERROR('Fleet growth and revenue'!J5<'Model inputs'!AA33),'Fleet growth and revenue'!J5<'Model inputs'!AA33,IF(OR('Fleet growth and revenue'!J5="",'Model inputs'!AA33=""),"",'Fleet growth and revenue'!J5<'Model inputs'!AA33))),0,ROUND('Model inputs'!AA32+('Model inputs'!AA31-'Model inputs'!AA32)*('Fleet growth and revenue'!J5-'Model inputs'!AA33)/('Model inputs'!AA34-'Model inputs'!AA33),0)) -> 19 | K6: =IF(IF(IF(ISERROR('Fleet growth and revenue'!K5<'Model inputs'!AA33),'Fleet growth and revenue'!K5<'Model inputs'!AA33,IF(OR('Fleet growth and revenue'!K5="",'Model inputs'!AA33=""),"",'Fleet growth and revenue'!K5<'Model inputs'!AA33))="",FALSE,IF(ISERROR('Fleet growth and revenue'!K5<'Model inputs'!AA33),'Fleet growth and revenue'!K5<'Model inputs'!AA33,IF(OR('Fleet growth and revenue'!K5="",'Model inputs'!AA33=""),"",'Fleet growth and revenue'!K5<'Model inputs'!AA33))),0,ROUND('Model inputs'!AA32+('Model inputs'!AA31-'Model inputs'!AA32)*('Fleet growth and revenue'!K5-'Model inputs'!AA33)/('Model inputs'!AA34-'Model inputs'!AA33),0)) -> 22 | L6: =IF(IF(IF(ISERROR('Fleet growth and revenue'!L5<'Model inputs'!AA33),'Fleet growth and revenue'!L5<'Model inputs'!AA33,IF(OR('Fleet growth and revenue'!L5="",'Model inputs'!AA33=""),"",'Fleet growth and revenue'!L5<'Model inputs'!AA33))="",FALSE,IF(ISERROR('Fleet growth and revenue'!L5<'Model inputs'!AA33),'Fleet growth and revenue'!L5<'Model inputs'!AA33,IF(OR('Fleet growth and revenue'!L5="",'Model inputs'!AA33=""),"",'Fleet growth and revenue'!L5<'Model inputs'!AA33))),0,ROUND('Model inputs'!AA32+('Model inputs'!AA31-'Model inputs'!AA32)*('Fleet growth and revenue'!L5-'Model inputs'!AA33)/('Model inputs'!AA34-'Model inputs'!AA33),0)) -> 25 | M6: =IF(IF(IF(ISERROR('Fleet growth and revenue'!M5<'Model inputs'!AA33),'Fleet growth and revenue'!M5<'Model inputs'!AA33,IF(OR('Fleet growth and revenue'!M5="",'Model inputs'!AA33=""),"",'Fleet growth and revenue'!M5<'Model inputs'!AA33))="",FALSE,IF(ISERROR('Fleet growth and revenue'!M5<'Model inputs'!AA33),'Fleet growth and revenue'!M5<'Model inputs'!AA33,IF(OR('Fleet growth and revenue'!M5="",'Model inputs'!AA33=""),"",'Fleet growth and revenue'!M5<'Model inputs'!AA33))),0,ROUND('Model inputs'!AA32+('Model inputs'!AA31-'Model inputs'!AA32)*('Fleet growth and revenue'!M5-'Model inputs'!AA33)/('Model inputs'!AA34-'Model inputs'!AA33),0)) -> 27 | N6: =IF(IF(IF(ISERROR('Fleet growth and revenue'!N5<'Model inputs'!AA33),'Fleet growth and revenue'!N5<'Model inputs'!AA33,IF(OR('Fleet growth and revenue'!N5="",'Model inputs'!AA33=""),"",'Fleet growth and revenue'!N5<'Model inputs'!AA33))="",FALSE,IF(ISERROR('Fleet growth and revenue'!N5<'Model inputs'!AA33),'Fleet growth and revenue'!N5<'Model inputs'!AA33,IF(OR('Fleet growth and revenue'!N5="",'Model inputs'!AA33=""),"",'Fleet growth and revenue'!N5<'Model inputs'!AA33))),0,ROUND('Model inputs'!AA32+('Model inputs'!AA31-'Model inputs'!AA32)*('Fleet growth and revenue'!N5-'Model inputs'!AA33)/('Model inputs'!AA34-'Model inputs'!AA33),0)) -> 30 | O6: =IF(IF(IF(ISERROR('Fleet growth and revenue'!O5<'Model inputs'!AA33),'Fleet growth and revenue'!O5<'Model inputs'!AA33,IF(OR('Fleet growth and revenue'!O5="",'Model inputs'!AA33=""),"",'Fleet growth and revenue'!O5<'Model inputs'!AA33))="",FALSE,IF(ISERROR('Fleet growth and revenue'!O5<'Model inputs'!AA33),'Fleet growth and revenue'!O5<'Model inputs'!AA33,IF(OR('Fleet growth and revenue'!O5="",'Model inputs'!AA33=""),"",'Fleet growth and revenue'!O5<'Model inputs'!AA33))),0,ROUND('Model inputs'!AA32+('Model inputs'!AA31-'Model inputs'!AA32)*('Fleet growth and revenue'!O5-'Model inputs'!AA33)/('Model inputs'!AA34-'Model inputs'!AA33),0)) -> 33 | P6: =IF(IF(IF(ISERROR('Fleet growth and revenue'!P5<'Model inputs'!AA33),'Fleet growth and revenue'!P5<'Model inputs'!AA33,IF(OR('Fleet growth and revenue'!P5="",'Model inputs'!AA33=""),"",'Fleet growth and revenue'!P5<'Model inputs'!AA33))="",FALSE,IF(ISERROR('Fleet growth and revenue'!P5<'Model inputs'!AA33),'Fleet growth and revenue'!P5<'Model inputs'!AA33,IF(OR('Fleet growth and revenue'!P5="",'Model inputs'!AA33=""),"",'Fleet growth and revenue'!P5<'Model inputs'!AA33))),0,ROUND('Model inputs'!AA32+('Model inputs'!AA31-'Model inputs'!AA32)*('Fleet growth and revenue'!P5-'Model inputs'!AA33)/('Model inputs'!AA34-'Model inputs'!AA33),0)) -> 36 | Q6: =IF(IF(IF(ISERROR('Fleet growth and revenue'!Q5<'Model inputs'!AA33),'Fleet growth and revenue'!Q5<'Model inputs'!AA33,IF(OR('Fleet growth and revenue'!Q5="",'Model inputs'!AA33=""),"",'Fleet growth and revenue'!Q5<'Model inputs'!AA33))="",FALSE,IF(ISERROR('Fleet growth and revenue'!Q5<'Model inputs'!AA33),'Fleet growth and revenue'!Q5<'Model inputs'!AA33,IF(OR('Fleet growth and revenue'!Q5="",'Model inputs'!AA33=""),"",'Fleet growth and revenue'!Q5<'Model inputs'!AA33))),0,ROUND('Model inputs'!AA32+('Model inputs'!AA31-'Model inputs'!AA32)*('Fleet growth and revenue'!Q5-'Model inputs'!AA33)/('Model inputs'!AA34-'Model inputs'!AA33),0)) -> 38 | R6: =IF(IF(IF(ISERROR('Fleet growth and revenue'!R5<'Model inputs'!AA33),'Fleet growth and revenue'!R5<'Model inputs'!AA33,IF(OR('Fleet growth and revenue'!R5="",'Model inputs'!AA33=""),"",'Fleet growth and revenue'!R5<'Model inputs'!AA33))="",FALSE,IF(ISERROR('Fleet growth and revenue'!R5<'Model inputs'!AA33),'Fleet growth and revenue'!R5<'Model inputs'!AA33,IF(OR('Fleet growth and revenue'!R5="",'Model inputs'!AA33=""),"",'Fleet growth and revenue'!R5<'Model inputs'!AA33))),0,ROUND('Model inputs'!AA32+('Model inputs'!AA31-'Model inputs'!AA32)*('Fleet growth and revenue'!R5-'Model inputs'!AA33)/('Model inputs'!AA34-'Model inputs'!AA33),0)) -> 41 | S6: =IF(IF(IF(ISERROR('Fleet growth and revenue'!S5<'Model inputs'!AA33),'Fleet growth and revenue'!S5<'Model inputs'!AA33,IF(OR('Fleet growth and revenue'!S5="",'Model inputs'!AA33=""),"",'Fleet growth and revenue'!S5<'Model inputs'!AA33))="",FALSE,IF(ISERROR('Fleet growth and revenue'!S5<'Model inputs'!AA33),'Fleet growth and revenue'!S5<'Model inputs'!AA33,IF(OR('Fleet growth and revenue'!S5="",'Model inputs'!AA33=""),"",'Fleet growth and revenue'!S5<'Model inputs'!AA33))),0,ROUND('Model inputs'!AA32+('Model inputs'!AA31-'Model inputs'!AA32)*('Fleet growth and revenue'!S5-'Model inputs'!AA33)/('Model inputs'!AA34-'Model inputs'!AA33),0)) -> 44 | T6: =IF(IF(IF(ISERROR('Fleet growth and revenue'!T5<'Model inputs'!AA33),'Fleet growth and revenue'!T5<'Model inputs'!AA33,IF(OR('Fleet growth and revenue'!T5="",'Model inputs'!AA33=""),"",'Fleet growth and revenue'!T5<'Model inputs'!AA33))="",FALSE,IF(ISERROR('Fleet growth and revenue'!T5<'Model inputs'!AA33),'Fleet growth and revenue'!T5<'Model inputs'!AA33,IF(OR('Fleet growth and revenue'!T5="",'Model inputs'!AA33=""),"",'Fleet growth and revenue'!T5<'Model inputs'!AA33))),0,ROUND('Model inputs'!AA32+('Model inputs'!AA31-'Model inputs'!AA32)*('Fleet growth and revenue'!T5-'Model inputs'!AA33)/('Model inputs'!AA34-'Model inputs'!AA33),0)) -> 46 | U6: =IF(IF(IF(ISERROR('Fleet growth and revenue'!U5<'Model inputs'!AA33),'Fleet growth and revenue'!U5<'Model inputs'!AA33,IF(OR('Fleet growth and revenue'!U5="",'Model inputs'!AA33=""),"",'Fleet growth and revenue'!U5<'Model inputs'!AA33))="",FALSE,IF(ISERROR('Fleet growth and revenue'!U5<'Model inputs'!AA33),'Fleet growth and revenue'!U5<'Model inputs'!AA33,IF(OR('Fleet growth and revenue'!U5="",'Model inputs'!AA33=""),"",'Fleet growth and revenue'!U5<'Model inputs'!AA33))),0,ROUND('Model inputs'!AA32+('Model inputs'!AA31-'Model inputs'!AA32)*('Fleet growth and revenue'!U5-'Model inputs'!AA33)/('Model inputs'!AA34-'Model inputs'!AA33),0)) -> 49 | V6: =IF(IF(IF(ISERROR('Fleet growth and revenue'!V5<'Model inputs'!AA33),'Fleet growth and revenue'!V5<'Model inputs'!AA33,IF(OR('Fleet growth and revenue'!V5="",'Model inputs'!AA33=""),"",'Fleet growth and revenue'!V5<'Model inputs'!AA33))="",FALSE,IF(ISERROR('Fleet growth and revenue'!V5<'Model inputs'!AA33),'Fleet growth and revenue'!V5<'Model inputs'!AA33,IF(OR('Fleet growth and revenue'!V5="",'Model inputs'!AA33=""),"",'Fleet growth and revenue'!V5<'Model inputs'!AA33))),0,ROUND('Model inputs'!AA32+('Model inputs'!AA31-'Model inputs'!AA32)*('Fleet growth and revenue'!V5-'Model inputs'!AA33)/('Model inputs'!AA34-'Model inputs'!AA33),0)) -> 52 | W6: =IF(IF(IF(ISERROR('Fleet growth and revenue'!W5<'Model inputs'!AA33),'Fleet growth and revenue'!W5<'Model inputs'!AA33,IF(OR('Fleet growth and revenue'!W5="",'Model inputs'!AA33=""),"",'Fleet growth and revenue'!W5<'Model inputs'!AA33))="",FALSE,IF(ISERROR('Fleet growth and revenue'!W5<'Model inputs'!AA33),'Fleet growth and revenue'!W5<'Model inputs'!AA33,IF(OR('Fleet growth and revenue'!W5="",'Model inputs'!AA33=""),"",'Fleet growth and revenue'!W5<'Model inputs'!AA33))),0,ROUND('Model inputs'!AA32+('Model inputs'!AA31-'Model inputs'!AA32)*('Fleet growth and revenue'!W5-'Model inputs'!AA33)/('Model inputs'!AA34-'Model inputs'!AA33),0)) -> 55 | X6: =IF(IF(IF(ISERROR('Fleet growth and revenue'!X5<'Model inputs'!AA33),'Fleet growth and revenue'!X5<'Model inputs'!AA33,IF(OR('Fleet growth and revenue'!X5="",'Model inputs'!AA33=""),"",'Fleet growth and revenue'!X5<'Model inputs'!AA33))="",FALSE,IF(ISERROR('Fleet growth and revenue'!X5<'Model inputs'!AA33),'Fleet growth and revenue'!X5<'Model inputs'!AA33,IF(OR('Fleet growth and revenue'!X5="",'Model inputs'!AA33=""),"",'Fleet growth and revenue'!X5<'Model inputs'!AA33))),0,ROUND('Model inputs'!AA32+('Model inputs'!AA31-'Model inputs'!AA32)*('Fleet growth and revenue'!X5-'Model inputs'!AA33)/('Model inputs'!AA34-'Model inputs'!AA33),0)) -> 57 | Y6: =IF(IF(IF(ISERROR('Fleet growth and revenue'!Y5<'Model inputs'!AA33),'Fleet growth and revenue'!Y5<'Model inputs'!AA33,IF(OR('Fleet growth and revenue'!Y5="",'Model inputs'!AA33=""),"",'Fleet growth and revenue'!Y5<'Model inputs'!AA33))="",FALSE,IF(ISERROR('Fleet growth and revenue'!Y5<'Model inputs'!AA33),'Fleet growth and revenue'!Y5<'Model inputs'!AA33,IF(OR('Fleet growth and revenue'!Y5="",'Model inputs'!AA33=""),"",'Fleet growth and revenue'!Y5<'Model inputs'!AA33))),0,ROUND('Model inputs'!AA32+('Model inputs'!AA31-'Model inputs'!AA32)*('Fleet growth and revenue'!Y5-'Model inputs'!AA33)/('Model inputs'!AA34-'Model inputs'!AA33),0)) -> 60
A7: Large active fleets | B7: =IF(IF(IF(ISERROR('Fleet growth and revenue'!B5<'Model inputs'!AA10),'Fleet growth and revenue'!B5<'Model inputs'!AA10,IF(OR('Fleet growth and revenue'!B5="",'Model inputs'!AA10=""),"",'Fleet growth and revenue'!B5<'Model inputs'!AA10))="",FALSE,IF(ISERROR('Fleet growth and revenue'!B5<'Model inputs'!AA10),'Fleet growth and revenue'!B5<'Model inputs'!AA10,IF(OR('Fleet growth and revenue'!B5="",'Model inputs'!AA10=""),"",'Fleet growth and revenue'!B5<'Model inputs'!AA10))),0,ROUND(MAX(0,'Fleet growth and revenue'!B6-'Model inputs'!AA32)*'Model inputs'!AA13,0)) -> 0 | C7: =IF(IF(IF(ISERROR('Fleet growth and revenue'!C5<'Model inputs'!AA10),'Fleet growth and revenue'!C5<'Model inputs'!AA10,IF(OR('Fleet growth and revenue'!C5="",'Model inputs'!AA10=""),"",'Fleet growth and revenue'!C5<'Model inputs'!AA10))="",FALSE,IF(ISERROR('Fleet growth and revenue'!C5<'Model inputs'!AA10),'Fleet growth and revenue'!C5<'Model inputs'!AA10,IF(OR('Fleet growth and revenue'!C5="",'Model inputs'!AA10=""),"",'Fleet growth and revenue'!C5<'Model inputs'!AA10))),0,ROUND(MAX(0,'Fleet growth and revenue'!C6-'Model inputs'!AA32)*'Model inputs'!AA13,0)) -> 0 | D7: =IF(IF(IF(ISERROR('Fleet growth and revenue'!D5<'Model inputs'!AA10),'Fleet growth and revenue'!D5<'Model inputs'!AA10,IF(OR('Fleet growth and revenue'!D5="",'Model inputs'!AA10=""),"",'Fleet growth and revenue'!D5<'Model inputs'!AA10))="",FALSE,IF(ISERROR('Fleet growth and revenue'!D5<'Model inputs'!AA10),'Fleet growth and revenue'!D5<'Model inputs'!AA10,IF(OR('Fleet growth and revenue'!D5="",'Model inputs'!AA10=""),"",'Fleet growth and revenue'!D5<'Model inputs'!AA10))),0,ROUND(MAX(0,'Fleet growth and revenue'!D6-'Model inputs'!AA32)*'Model inputs'!AA13,0)) -> 0 | E7: =IF(IF(IF(ISERROR('Fleet growth and revenue'!E5<'Model inputs'!AA10),'Fleet growth and revenue'!E5<'Model inputs'!AA10,IF(OR('Fleet growth and revenue'!E5="",'Model inputs'!AA10=""),"",'Fleet growth and revenue'!E5<'Model inputs'!AA10))="",FALSE,IF(ISERROR('Fleet growth and revenue'!E5<'Model inputs'!AA10),'Fleet growth and revenue'!E5<'Model inputs'!AA10,IF(OR('Fleet growth and revenue'!E5="",'Model inputs'!AA10=""),"",'Fleet growth and revenue'!E5<'Model inputs'!AA10))),0,ROUND(MAX(0,'Fleet growth and revenue'!E6-'Model inputs'!AA32)*'Model inputs'!AA13,0)) -> 0 | F7: =IF(IF(IF(ISERROR('Fleet growth and revenue'!F5<'Model inputs'!AA10),'Fleet growth and revenue'!F5<'Model inputs'!AA10,IF(OR('Fleet growth and revenue'!F5="",'Model inputs'!AA10=""),"",'Fleet growth and revenue'!F5<'Model inputs'!AA10))="",FALSE,IF(ISERROR('Fleet growth and revenue'!F5<'Model inputs'!AA10),'Fleet growth and revenue'!F5<'Model inputs'!AA10,IF(OR('Fleet growth and revenue'!F5="",'Model inputs'!AA10=""),"",'Fleet growth and revenue'!F5<'Model inputs'!AA10))),0,ROUND(MAX(0,'Fleet growth and revenue'!F6-'Model inputs'!AA32)*'Model inputs'!AA13,0)) -> 0 | G7: =IF(IF(IF(ISERROR('Fleet growth and revenue'!G5<'Model inputs'!AA10),'Fleet growth and revenue'!G5<'Model inputs'!AA10,IF(OR('Fleet growth and revenue'!G5="",'Model inputs'!AA10=""),"",'Fleet growth and revenue'!G5<'Model inputs'!AA10))="",FALSE,IF(ISERROR('Fleet growth and revenue'!G5<'Model inputs'!AA10),'Fleet growth and revenue'!G5<'Model inputs'!AA10,IF(OR('Fleet growth and revenue'!G5="",'Model inputs'!AA10=""),"",'Fleet growth and revenue'!G5<'Model inputs'!AA10))),0,ROUND(MAX(0,'Fleet growth and revenue'!G6-'Model inputs'!AA32)*'Model inputs'!AA13,0)) -> 2 | H7: =IF(IF(IF(ISERROR('Fleet growth and revenue'!H5<'Model inputs'!AA10),'Fleet growth and revenue'!H5<'Model inputs'!AA10,IF(OR('Fleet growth and revenue'!H5="",'Model inputs'!AA10=""),"",'Fleet growth and revenue'!H5<'Model inputs'!AA10))="",FALSE,IF(ISERROR('Fleet growth and revenue'!H5<'Model inputs'!AA10),'Fleet growth and revenue'!H5<'Model inputs'!AA10,IF(OR('Fleet growth and revenue'!H5="",'Model inputs'!AA10=""),"",'Fleet growth and revenue'!H5<'Model inputs'!AA10))),0,ROUND(MAX(0,'Fleet growth and revenue'!H6-'Model inputs'!AA32)*'Model inputs'!AA13,0)) -> 2 | I7: =IF(IF(IF(ISERROR('Fleet growth and revenue'!I5<'Model inputs'!AA10),'Fleet growth and revenue'!I5<'Model inputs'!AA10,IF(OR('Fleet growth and revenue'!I5="",'Model inputs'!AA10=""),"",'Fleet growth and revenue'!I5<'Model inputs'!AA10))="",FALSE,IF(ISERROR('Fleet growth and revenue'!I5<'Model inputs'!AA10),'Fleet growth and revenue'!I5<'Model inputs'!AA10,IF(OR('Fleet growth and revenue'!I5="",'Model inputs'!AA10=""),"",'Fleet growth and revenue'!I5<'Model inputs'!AA10))),0,ROUND(MAX(0,'Fleet growth and revenue'!I6-'Model inputs'!AA32)*'Model inputs'!AA13,0)) -> 3 | J7: =IF(IF(IF(ISERROR('Fleet growth and revenue'!J5<'Model inputs'!AA10),'Fleet growth and revenue'!J5<'Model inputs'!AA10,IF(OR('Fleet growth and revenue'!J5="",'Model inputs'!AA10=""),"",'Fleet growth and revenue'!J5<'Model inputs'!AA10))="",FALSE,IF(ISERROR('Fleet growth and revenue'!J5<'Model inputs'!AA10),'Fleet growth and revenue'!J5<'Model inputs'!AA10,IF(OR('Fleet growth and revenue'!J5="",'Model inputs'!AA10=""),"",'Fleet growth and revenue'!J5<'Model inputs'!AA10))),0,ROUND(MAX(0,'Fleet growth and revenue'!J6-'Model inputs'!AA32)*'Model inputs'!AA13,0)) -> 3 | K7: =IF(IF(IF(ISERROR('Fleet growth and revenue'!K5<'Model inputs'!AA10),'Fleet growth and revenue'!K5<'Model inputs'!AA10,IF(OR('Fleet growth and revenue'!K5="",'Model inputs'!AA10=""),"",'Fleet growth and revenue'!K5<'Model inputs'!AA10))="",FALSE,IF(ISERROR('Fleet growth and revenue'!K5<'Model inputs'!AA10),'Fleet growth and revenue'!K5<'Model inputs'!AA10,IF(OR('Fleet growth and revenue'!K5="",'Model inputs'!AA10=""),"",'Fleet growth and revenue'!K5<'Model inputs'!AA10))),0,ROUND(MAX(0,'Fleet growth and revenue'!K6-'Model inputs'!AA32)*'Model inputs'!AA13,0)) -> 4 | L7: =IF(IF(IF(ISERROR('Fleet growth and revenue'!L5<'Model inputs'!AA10),'Fleet growth and revenue'!L5<'Model inputs'!AA10,IF(OR('Fleet growth and revenue'!L5="",'Model inputs'!AA10=""),"",'Fleet growth and revenue'!L5<'Model inputs'!AA10))="",FALSE,IF(ISERROR('Fleet growth and revenue'!L5<'Model inputs'!AA10),'Fleet growth and revenue'!L5<'Model inputs'!AA10,IF(OR('Fleet growth and revenue'!L5="",'Model inputs'!AA10=""),"",'Fleet growth and revenue'!L5<'Model inputs'!AA10))),0,ROUND(MAX(0,'Fleet growth and revenue'!L6-'Model inputs'!AA32)*'Model inputs'!AA13,0)) -> 4 | M7: =IF(IF(IF(ISERROR('Fleet growth and revenue'!M5<'Model inputs'!AA10),'Fleet growth and revenue'!M5<'Model inputs'!AA10,IF(OR('Fleet growth and revenue'!M5="",'Model inputs'!AA10=""),"",'Fleet growth and revenue'!M5<'Model inputs'!AA10))="",FALSE,IF(ISERROR('Fleet growth and revenue'!M5<'Model inputs'!AA10),'Fleet growth and revenue'!M5<'Model inputs'!AA10,IF(OR('Fleet growth and revenue'!M5="",'Model inputs'!AA10=""),"",'Fleet growth and revenue'!M5<'Model inputs'!AA10))),0,ROUND(MAX(0,'Fleet growth and revenue'!M6-'Model inputs'!AA32)*'Model inputs'!AA13,0)) -> 5 | N7: =IF(IF(IF(ISERROR('Fleet growth and revenue'!N5<'Model inputs'!AA10),'Fleet growth and revenue'!N5<'Model inputs'!AA10,IF(OR('Fleet growth and revenue'!N5="",'Model inputs'!AA10=""),"",'Fleet growth and revenue'!N5<'Model inputs'!AA10))="",FALSE,IF(ISERROR('Fleet growth and revenue'!N5<'Model inputs'!AA10),'Fleet growth and revenue'!N5<'Model inputs'!AA10,IF(OR('Fleet growth and revenue'!N5="",'Model inputs'!AA10=""),"",'Fleet growth and revenue'!N5<'Model inputs'!AA10))),0,ROUND(MAX(0,'Fleet growth and revenue'!N6-'Model inputs'!AA32)*'Model inputs'!AA13,0)) -> 5 | O7: =IF(IF(IF(ISERROR('Fleet growth and revenue'!O5<'Model inputs'!AA10),'Fleet growth and revenue'!O5<'Model inputs'!AA10,IF(OR('Fleet growth and revenue'!O5="",'Model inputs'!AA10=""),"",'Fleet growth and revenue'!O5<'Model inputs'!AA10))="",FALSE,IF(ISERROR('Fleet growth and revenue'!O5<'Model inputs'!AA10),'Fleet growth and revenue'!O5<'Model inputs'!AA10,IF(OR('Fleet growth and revenue'!O5="",'Model inputs'!AA10=""),"",'Fleet growth and revenue'!O5<'Model inputs'!AA10))),0,ROUND(MAX(0,'Fleet growth and revenue'!O6-'Model inputs'!AA32)*'Model inputs'!AA13,0)) -> 6 | P7: =IF(IF(IF(ISERROR('Fleet growth and revenue'!P5<'Model inputs'!AA10),'Fleet growth and revenue'!P5<'Model inputs'!AA10,IF(OR('Fleet growth and revenue'!P5="",'Model inputs'!AA10=""),"",'Fleet growth and revenue'!P5<'Model inputs'!AA10))="",FALSE,IF(ISERROR('Fleet growth and revenue'!P5<'Model inputs'!AA10),'Fleet growth and revenue'!P5<'Model inputs'!AA10,IF(OR('Fleet growth and revenue'!P5="",'Model inputs'!AA10=""),"",'Fleet growth and revenue'!P5<'Model inputs'!AA10))),0,ROUND(MAX(0,'Fleet growth and revenue'!P6-'Model inputs'!AA32)*'Model inputs'!AA13,0)) -> 7 | Q7: =IF(IF(IF(ISERROR('Fleet growth and revenue'!Q5<'Model inputs'!AA10),'Fleet growth and revenue'!Q5<'Model inputs'!AA10,IF(OR('Fleet growth and revenue'!Q5="",'Model inputs'!AA10=""),"",'Fleet growth and revenue'!Q5<'Model inputs'!AA10))="",FALSE,IF(ISERROR('Fleet growth and revenue'!Q5<'Model inputs'!AA10),'Fleet growth and revenue'!Q5<'Model inputs'!AA10,IF(OR('Fleet growth and revenue'!Q5="",'Model inputs'!AA10=""),"",'Fleet growth and revenue'!Q5<'Model inputs'!AA10))),0,ROUND(MAX(0,'Fleet growth and revenue'!Q6-'Model inputs'!AA32)*'Model inputs'!AA13,0)) -> 7 | R7: =IF(IF(IF(ISERROR('Fleet growth and revenue'!R5<'Model inputs'!AA10),'Fleet growth and revenue'!R5<'Model inputs'!AA10,IF(OR('Fleet growth and revenue'!R5="",'Model inputs'!AA10=""),"",'Fleet growth and revenue'!R5<'Model inputs'!AA10))="",FALSE,IF(ISERROR('Fleet growth and revenue'!R5<'Model inputs'!AA10),'Fleet growth and revenue'!R5<'Model inputs'!AA10,IF(OR('Fleet growth and revenue'!R5="",'Model inputs'!AA10=""),"",'Fleet growth and revenue'!R5<'Model inputs'!AA10))),0,ROUND(MAX(0,'Fleet growth and revenue'!R6-'Model inputs'!AA32)*'Model inputs'!AA13,0)) -> 8 | S7: =IF(IF(IF(ISERROR('Fleet growth and revenue'!S5<'Model inputs'!AA10),'Fleet growth and revenue'!S5<'Model inputs'!AA10,IF(OR('Fleet growth and revenue'!S5="",'Model inputs'!AA10=""),"",'Fleet growth and revenue'!S5<'Model inputs'!AA10))="",FALSE,IF(ISERROR('Fleet growth and revenue'!S5<'Model inputs'!AA10),'Fleet growth and revenue'!S5<'Model inputs'!AA10,IF(OR('Fleet growth and revenue'!S5="",'Model inputs'!AA10=""),"",'Fleet growth and revenue'!S5<'Model inputs'!AA10))),0,ROUND(MAX(0,'Fleet growth and revenue'!S6-'Model inputs'!AA32)*'Model inputs'!AA13,0)) -> 8 | T7: =IF(IF(IF(ISERROR('Fleet growth and revenue'!T5<'Model inputs'!AA10),'Fleet growth and revenue'!T5<'Model inputs'!AA10,IF(OR('Fleet growth and revenue'!T5="",'Model inputs'!AA10=""),"",'Fleet growth and revenue'!T5<'Model inputs'!AA10))="",FALSE,IF(ISERROR('Fleet growth and revenue'!T5<'Model inputs'!AA10),'Fleet growth and revenue'!T5<'Model inputs'!AA10,IF(OR('Fleet growth and revenue'!T5="",'Model inputs'!AA10=""),"",'Fleet growth and revenue'!T5<'Model inputs'!AA10))),0,ROUND(MAX(0,'Fleet growth and revenue'!T6-'Model inputs'!AA32)*'Model inputs'!AA13,0)) -> 9 | U7: =IF(IF(IF(ISERROR('Fleet growth and revenue'!U5<'Model inputs'!AA10),'Fleet growth and revenue'!U5<'Model inputs'!AA10,IF(OR('Fleet growth and revenue'!U5="",'Model inputs'!AA10=""),"",'Fleet growth and revenue'!U5<'Model inputs'!AA10))="",FALSE,IF(ISERROR('Fleet growth and revenue'!U5<'Model inputs'!AA10),'Fleet growth and revenue'!U5<'Model inputs'!AA10,IF(OR('Fleet growth and revenue'!U5="",'Model inputs'!AA10=""),"",'Fleet growth and revenue'!U5<'Model inputs'!AA10))),0,ROUND(MAX(0,'Fleet growth and revenue'!U6-'Model inputs'!AA32)*'Model inputs'!AA13,0)) -> 9 | V7: =IF(IF(IF(ISERROR('Fleet growth and revenue'!V5<'Model inputs'!AA10),'Fleet growth and revenue'!V5<'Model inputs'!AA10,IF(OR('Fleet growth and revenue'!V5="",'Model inputs'!AA10=""),"",'Fleet growth and revenue'!V5<'Model inputs'!AA10))="",FALSE,IF(ISERROR('Fleet growth and revenue'!V5<'Model inputs'!AA10),'Fleet growth and revenue'!V5<'Model inputs'!AA10,IF(OR('Fleet growth and revenue'!V5="",'Model inputs'!AA10=""),"",'Fleet growth and revenue'!V5<'Model inputs'!AA10))),0,ROUND(MAX(0,'Fleet growth and revenue'!V6-'Model inputs'!AA32)*'Model inputs'!AA13,0)) -> 10 | W7: =IF(IF(IF(ISERROR('Fleet growth and revenue'!W5<'Model inputs'!AA10),'Fleet growth and revenue'!W5<'Model inputs'!AA10,IF(OR('Fleet growth and revenue'!W5="",'Model inputs'!AA10=""),"",'Fleet growth and revenue'!W5<'Model inputs'!AA10))="",FALSE,IF(ISERROR('Fleet growth and revenue'!W5<'Model inputs'!AA10),'Fleet growth and revenue'!W5<'Model inputs'!AA10,IF(OR('Fleet growth and revenue'!W5="",'Model inputs'!AA10=""),"",'Fleet growth and revenue'!W5<'Model inputs'!AA10))),0,ROUND(MAX(0,'Fleet growth and revenue'!W6-'Model inputs'!AA32)*'Model inputs'!AA13,0)) -> 10 | X7: =IF(IF(IF(ISERROR('Fleet growth and revenue'!X5<'Model inputs'!AA10),'Fleet growth and revenue'!X5<'Model inputs'!AA10,IF(OR('Fleet growth and revenue'!X5="",'Model inputs'!AA10=""),"",'Fleet growth and revenue'!X5<'Model inputs'!AA10))="",FALSE,IF(ISERROR('Fleet growth and revenue'!X5<'Model inputs'!AA10),'Fleet growth and revenue'!X5<'Model inputs'!AA10,IF(OR('Fleet growth and revenue'!X5="",'Model inputs'!AA10=""),"",'Fleet growth and revenue'!X5<'Model inputs'!AA10))),0,ROUND(MAX(0,'Fleet growth and revenue'!X6-'Model inputs'!AA32)*'Model inputs'!AA13,0)) -> 11 | Y7: =IF(IF(IF(ISERROR('Fleet growth and revenue'!Y5<'Model inputs'!AA10),'Fleet growth and revenue'!Y5<'Model inputs'!AA10,IF(OR('Fleet growth and revenue'!Y5="",'Model inputs'!AA10=""),"",'Fleet growth and revenue'!Y5<'Model inputs'!AA10))="",FALSE,IF(ISERROR('Fleet growth and revenue'!Y5<'Model inputs'!AA10),'Fleet growth and revenue'!Y5<'Model inputs'!AA10,IF(OR('Fleet growth and revenue'!Y5="",'Model inputs'!AA10=""),"",'Fleet growth and revenue'!Y5<'Model inputs'!AA10))),0,ROUND(MAX(0,'Fleet growth and revenue'!Y6-'Model inputs'!AA32)*'Model inputs'!AA13,0)) -> 11
A8: Active fleets | B8: =SUM('Fleet growth and revenue'!B9,'Fleet growth and revenue'!B10) -> 0 | C8: =SUM('Fleet growth and revenue'!C9,'Fleet growth and revenue'!C10) -> 0 | D8: =SUM('Fleet growth and revenue'!D9,'Fleet growth and revenue'!D10) -> 3 | E8: =SUM('Fleet growth and revenue'!E9,'Fleet growth and revenue'!E10) -> 6 | F8: =SUM('Fleet growth and revenue'!F9,'Fleet growth and revenue'!F10) -> 8 | G8: =SUM('Fleet growth and revenue'!G9,'Fleet growth and revenue'!G10) -> 11 | H8: =SUM('Fleet growth and revenue'!H9,'Fleet growth and revenue'!H10) -> 14 | I8: =SUM('Fleet growth and revenue'!I9,'Fleet growth and revenue'!I10) -> 17 | ... Y8: =SUM('Fleet growth and revenue'!Y9,'Fleet growth and revenue'!Y10) -> 60
A9: 30-van fleets | B9: =IF(EXACT("30-van fleets","80-van fleets"),IF('Fleet growth and revenue'!B7="","",'Fleet growth and revenue'!B7),'Fleet growth and revenue'!B6-'Fleet growth and revenue'!B7) -> 0 | C9: =IF(EXACT("30-van fleets","80-van fleets"),IF('Fleet growth and revenue'!C7="","",'Fleet growth and revenue'!C7),'Fleet growth and revenue'!C6-'Fleet growth and revenue'!C7) -> 0 | D9: =IF(EXACT("30-van fleets","80-van fleets"),IF('Fleet growth and revenue'!D7="","",'Fleet growth and revenue'!D7),'Fleet growth and revenue'!D6-'Fleet growth and revenue'!D7) -> 3 | E9: =IF(EXACT("30-van fleets","80-van fleets"),IF('Fleet growth and revenue'!E7="","",'Fleet growth and revenue'!E7),'Fleet growth and revenue'!E6-'Fleet growth and revenue'!E7) -> 6 | F9: =IF(EXACT("30-van fleets","80-van fleets"),IF('Fleet growth and revenue'!F7="","",'Fleet growth and revenue'!F7),'Fleet growth and revenue'!F6-'Fleet growth and revenue'!F7) -> 8 | G9: =IF(EXACT("30-van fleets","80-van fleets"),IF('Fleet growth and revenue'!G7="","",'Fleet growth and revenue'!G7),'Fleet growth and revenue'!G6-'Fleet growth and revenue'!G7) -> 9 | H9: =IF(EXACT("30-van fleets","80-van fleets"),IF('Fleet growth and revenue'!H7="","",'Fleet growth and revenue'!H7),'Fleet growth and revenue'!H6-'Fleet growth and revenue'!H7) -> 12 | I9: =IF(EXACT("30-van fleets","80-van fleets"),IF('Fleet growth and revenue'!I7="","",'Fleet growth and revenue'!I7),'Fleet growth and revenue'!I6-'Fleet growth and revenue'!I7) -> 14 | ... Y9: =IF(EXACT("30-van fleets","80-van fleets"),IF('Fleet growth and revenue'!Y7="","",'Fleet growth and revenue'!Y7),'Fleet growth and revenue'!Y6-'Fleet growth and revenue'!Y7) -> 49
A10: 80-van fleets | B10: =IF(EXACT("80-van fleets","80-van fleets"),IF('Fleet growth and revenue'!B7="","",'Fleet growth and revenue'!B7),'Fleet growth and revenue'!B6-'Fleet growth and revenue'!B7) -> 0 | C10: =IF(EXACT("80-van fleets","80-van fleets"),IF('Fleet growth and revenue'!C7="","",'Fleet growth and revenue'!C7),'Fleet growth and revenue'!C6-'Fleet growth and revenue'!C7) -> 0 | D10: =IF(EXACT("80-van fleets","80-van fleets"),IF('Fleet growth and revenue'!D7="","",'Fleet growth and revenue'!D7),'Fleet growth and revenue'!D6-'Fleet growth and revenue'!D7) -> 0 | E10: =IF(EXACT("80-van fleets","80-van fleets"),IF('Fleet growth and revenue'!E7="","",'Fleet growth and revenue'!E7),'Fleet growth and revenue'!E6-'Fleet growth and revenue'!E7) -> 0 | F10: =IF(EXACT("80-van fleets","80-van fleets"),IF('Fleet growth and revenue'!F7="","",'Fleet growth and revenue'!F7),'Fleet growth and revenue'!F6-'Fleet growth and revenue'!F7) -> 0 | G10: =IF(EXACT("80-van fleets","80-van fleets"),IF('Fleet growth and revenue'!G7="","",'Fleet growth and revenue'!G7),'Fleet growth and revenue'!G6-'Fleet growth and revenue'!G7) -> 2 | H10: =IF(EXACT("80-van fleets","80-van fleets"),IF('Fleet growth and revenue'!H7="","",'Fleet growth and revenue'!H7),'Fleet growth and revenue'!H6-'Fleet growth and revenue'!H7) -> 2 | I10: =IF(EXACT("80-van fleets","80-van fleets"),IF('Fleet growth and revenue'!I7="","",'Fleet growth and revenue'!I7),'Fleet growth and revenue'!I6-'Fleet growth and revenue'!I7) -> 3 | ... Y10: =IF(EXACT("80-van fleets","80-van fleets"),IF('Fleet growth and revenue'!Y7="","",'Fleet growth and revenue'!Y7),'Fleet growth and revenue'!Y6-'Fleet growth and revenue'!Y7) -> 11
A11: Active vans | B11: =SUM('Fleet growth and revenue'!B12,'Fleet growth and revenue'!B13) -> 0 | C11: =SUM('Fleet growth and revenue'!C12,'Fleet growth and revenue'!C13) -> 0 | D11: =SUM('Fleet growth and revenue'!D12,'Fleet growth and revenue'!D13) -> 90 | E11: =SUM('Fleet growth and revenue'!E12,'Fleet growth and revenue'!E13) -> 180 | F11: =SUM('Fleet growth and revenue'!F12,'Fleet growth and revenue'!F13) -> 240 | G11: =SUM('Fleet growth and revenue'!G12,'Fleet growth and revenue'!G13) -> 430 | H11: =SUM('Fleet growth and revenue'!H12,'Fleet growth and revenue'!H13) -> 520 | I11: =SUM('Fleet growth and revenue'!I12,'Fleet growth and revenue'!I13) -> 660 | ... Y11: =SUM('Fleet growth and revenue'!Y12,'Fleet growth and revenue'!Y13) -> 2350
A12: 30-van fleets | B12: ='Fleet growth and revenue'!B9*IF(IF(EXACT("30-van fleets","80-van fleets"),IF('Model inputs'!AA14="","",'Model inputs'!AA14),IF('Model inputs'!AA27="","",'Model inputs'!AA27))="",0,IF(EXACT("30-van fleets","80-van fleets"),IF('Model inputs'!AA14="","",'Model inputs'!AA14),IF('Model inputs'!AA27="","",'Model inputs'!AA27))) -> 0 | C12: ='Fleet growth and revenue'!C9*IF(IF(EXACT("30-van fleets","80-van fleets"),IF('Model inputs'!AA14="","",'Model inputs'!AA14),IF('Model inputs'!AA27="","",'Model inputs'!AA27))="",0,IF(EXACT("30-van fleets","80-van fleets"),IF('Model inputs'!AA14="","",'Model inputs'!AA14),IF('Model inputs'!AA27="","",'Model inputs'!AA27))) -> 0 | D12: ='Fleet growth and revenue'!D9*IF(IF(EXACT("30-van fleets","80-van fleets"),IF('Model inputs'!AA14="","",'Model inputs'!AA14),IF('Model inputs'!AA27="","",'Model inputs'!AA27))="",0,IF(EXACT("30-van fleets","80-van fleets"),IF('Model inputs'!AA14="","",'Model inputs'!AA14),IF('Model inputs'!AA27="","",'Model inputs'!AA27))) -> 90 | E12: ='Fleet growth and revenue'!E9*IF(IF(EXACT("30-van fleets","80-van fleets"),IF('Model inputs'!AA14="","",'Model inputs'!AA14),IF('Model inputs'!AA27="","",'Model inputs'!AA27))="",0,IF(EXACT("30-van fleets","80-van fleets"),IF('Model inputs'!AA14="","",'Model inputs'!AA14),IF('Model inputs'!AA27="","",'Model inputs'!AA27))) -> 180 | F12: ='Fleet growth and revenue'!F9*IF(IF(EXACT("30-van fleets","80-van fleets"),IF('Model inputs'!AA14="","",'Model inputs'!AA14),IF('Model inputs'!AA27="","",'Model inputs'!AA27))="",0,IF(EXACT("30-van fleets","80-van fleets"),IF('Model inputs'!AA14="","",'Model inputs'!AA14),IF('Model inputs'!AA27="","",'Model inputs'!AA27))) -> 240 | G12: ='Fleet growth and revenue'!G9*IF(IF(EXACT("30-van fleets","80-van fleets"),IF('Model inputs'!AA14="","",'Model inputs'!AA14),IF('Model inputs'!AA27="","",'Model inputs'!AA27))="",0,IF(EXACT("30-van fleets","80-van fleets"),IF('Model inputs'!AA14="","",'Model inputs'!AA14),IF('Model inputs'!AA27="","",'Model inputs'!AA27))) -> 270 | H12: ='Fleet growth and revenue'!H9*IF(IF(EXACT("30-van fleets","80-van fleets"),IF('Model inputs'!AA14="","",'Model inputs'!AA14),IF('Model inputs'!AA27="","",'Model inputs'!AA27))="",0,IF(EXACT("30-van fleets","80-van fleets"),IF('Model inputs'!AA14="","",'Model inputs'!AA14),IF('Model inputs'!AA27="","",'Model inputs'!AA27))) -> 360 | I12: ='Fleet growth and revenue'!I9*IF(IF(EXACT("30-van fleets","80-van fleets"),IF('Model inputs'!AA14="","",'Model inputs'!AA14),IF('Model inputs'!AA27="","",'Model inputs'!AA27))="",0,IF(EXACT("30-van fleets","80-van fleets"),IF('Model inputs'!AA14="","",'Model inputs'!AA14),IF('Model inputs'!AA27="","",'Model inputs'!AA27))) -> 420 | J12: ='Fleet growth and revenue'!J9*IF(IF(EXACT("30-van fleets","80-van fleets"),IF('Model inputs'!AA14="","",'Model inputs'!AA14),IF('Model inputs'!AA27="","",'Model inputs'!AA27))="",0,IF(EXACT("30-van fleets","80-van fleets"),IF('Model inputs'!AA14="","",'Model inputs'!AA14),IF('Model inputs'!AA27="","",'Model inputs'!AA27))) -> 480 | K12: ='Fleet growth and revenue'!K9*IF(IF(EXACT("30-van fleets","80-van fleets"),IF('Model inputs'!AA14="","",'Model inputs'!AA14),IF('Model inputs'!AA27="","",'Model inputs'!AA27))="",0,IF(EXACT("30-van fleets","80-van fleets"),IF('Model inputs'!AA14="","",'Model inputs'!AA14),IF('Model inputs'!AA27="","",'Model inputs'!AA27))) -> 540 | L12: ='Fleet growth and revenue'!L9*IF(IF(EXACT("30-van fleets","80-van fleets"),IF('Model inputs'!AA14="","",'Model inputs'!AA14),IF('Model inputs'!AA27="","",'Model inputs'!AA27))="",0,IF(EXACT("30-van fleets","80-van fleets"),IF('Model inputs'!AA14="","",'Model inputs'!AA14),IF('Model inputs'!AA27="","",'Model inputs'!AA27))) -> 630 | M12: ='Fleet growth and revenue'!M9*IF(IF(EXACT("30-van fleets","80-van fleets"),IF('Model inputs'!AA14="","",'Model inputs'!AA14),IF('Model inputs'!AA27="","",'Model inputs'!AA27))="",0,IF(EXACT("30-van fleets","80-van fleets"),IF('Model inputs'!AA14="","",'Model inputs'!AA14),IF('Model inputs'!AA27="","",'Model inputs'!AA27))) -> 660 | N12: ='Fleet growth and revenue'!N9*IF(IF(EXACT("30-van fleets","80-van fleets"),IF('Model inputs'!AA14="","",'Model inputs'!AA14),IF('Model inputs'!AA27="","",'Model inputs'!AA27))="",0,IF(EXACT("30-van fleets","80-van fleets"),IF('Model inputs'!AA14="","",'Model inputs'!AA14),IF('Model inputs'!AA27="","",'Model inputs'!AA27))) -> 750 | O12: ='Fleet growth and revenue'!O9*IF(IF(EXACT("30-van fleets","80-van fleets"),IF('Model inputs'!AA14="","",'Model inputs'!AA14),IF('Model inputs'!AA27="","",'Model inputs'!AA27))="",0,IF(EXACT("30-van fleets","80-van fleets"),IF('Model inputs'!AA14="","",'Model inputs'!AA14),IF('Model inputs'!AA27="","",'Model inputs'!AA27))) -> 810 | P12: ='Fleet growth and revenue'!P9*IF(IF(EXACT("30-van fleets","80-van fleets"),IF('Model inputs'!AA14="","",'Model inputs'!AA14),IF('Model inputs'!AA27="","",'Model inputs'!AA27))="",0,IF(EXACT("30-van fleets","80-van fleets"),IF('Model inputs'!AA14="","",'Model inputs'!AA14),IF('Model inputs'!AA27="","",'Model inputs'!AA27))) -> 870 | Q12: ='Fleet growth and revenue'!Q9*IF(IF(EXACT("30-van fleets","80-van fleets"),IF('Model inputs'!AA14="","",'Model inputs'!AA14),IF('Model inputs'!AA27="","",'Model inputs'!AA27))="",0,IF(EXACT("30-van fleets","80-van fleets"),IF('Model inputs'!AA14="","",'Model inputs'!AA14),IF('Model inputs'!AA27="","",'Model inputs'!AA27))) -> 930 | R12: ='Fleet growth and revenue'!R9*IF(IF(EXACT("30-van fleets","80-van fleets"),IF('Model inputs'!AA14="","",'Model inputs'!AA14),IF('Model inputs'!AA27="","",'Model inputs'!AA27))="",0,IF(EXACT("30-van fleets","80-van fleets"),IF('Model inputs'!AA14="","",'Model inputs'!AA14),IF('Model inputs'!AA27="","",'Model inputs'!AA27))) -> 990 | S12: ='Fleet growth and revenue'!S9*IF(IF(EXACT("30-van fleets","80-van fleets"),IF('Model inputs'!AA14="","",'Model inputs'!AA14),IF('Model inputs'!AA27="","",'Model inputs'!AA27))="",0,IF(EXACT("30-van fleets","80-van fleets"),IF('Model inputs'!AA14="","",'Model inputs'!AA14),IF('Model inputs'!AA27="","",'Model inputs'!AA27))) -> 1080 | T12: ='Fleet growth and revenue'!T9*IF(IF(EXACT("30-van fleets","80-van fleets"),IF('Model inputs'!AA14="","",'Model inputs'!AA14),IF('Model inputs'!AA27="","",'Model inputs'!AA27))="",0,IF(EXACT("30-van fleets","80-van fleets"),IF('Model inputs'!AA14="","",'Model inputs'!AA14),IF('Model inputs'!AA27="","",'Model inputs'!AA27))) -> 1110 | U12: ='Fleet growth and revenue'!U9*IF(IF(EXACT("30-van fleets","80-van fleets"),IF('Model inputs'!AA14="","",'Model inputs'!AA14),IF('Model inputs'!AA27="","",'Model inputs'!AA27))="",0,IF(EXACT("30-van fleets","80-van fleets"),IF('Model inputs'!AA14="","",'Model inputs'!AA14),IF('Model inputs'!AA27="","",'Model inputs'!AA27))) -> 1200 | V12: ='Fleet growth and revenue'!V9*IF(IF(EXACT("30-van fleets","80-van fleets"),IF('Model inputs'!AA14="","",'Model inputs'!AA14),IF('Model inputs'!AA27="","",'Model inputs'!AA27))="",0,IF(EXACT("30-van fleets","80-van fleets"),IF('Model inputs'!AA14="","",'Model inputs'!AA14),IF('Model inputs'!AA27="","",'Model inputs'!AA27))) -> 1260 | W12: ='Fleet growth and revenue'!W9*IF(IF(EXACT("30-van fleets","80-van fleets"),IF('Model inputs'!AA14="","",'Model inputs'!AA14),IF('Model inputs'!AA27="","",'Model inputs'!AA27))="",0,IF(EXACT("30-van fleets","80-van fleets"),IF('Model inputs'!AA14="","",'Model inputs'!AA14),IF('Model inputs'!AA27="","",'Model inputs'!AA27))) -> 1350 | X12: ='Fleet growth and revenue'!X9*IF(IF(EXACT("30-van fleets","80-van fleets"),IF('Model inputs'!AA14="","",'Model inputs'!AA14),IF('Model inputs'!AA27="","",'Model inputs'!AA27))="",0,IF(EXACT("30-van fleets","80-van fleets"),IF('Model inputs'!AA14="","",'Model inputs'!AA14),IF('Model inputs'!AA27="","",'Model inputs'!AA27))) -> 1380 | Y12: ='Fleet growth and revenue'!Y9*IF(IF(EXACT("30-van fleets","80-van fleets"),IF('Model inputs'!AA14="","",'Model inputs'!AA14),IF('Model inputs'!AA27="","",'Model inputs'!AA27))="",0,IF(EXACT("30-van fleets","80-van fleets"),IF('Model inputs'!AA14="","",'Model inputs'!AA14),IF('Model inputs'!AA27="","",'Model inputs'!AA27))) -> 1470
A13: 80-van fleets | B13: ='Fleet growth and revenue'!B10*IF(IF(EXACT("80-van fleets","80-van fleets"),IF('Model inputs'!AA14="","",'Model inputs'!AA14),IF('Model inputs'!AA27="","",'Model inputs'!AA27))="",0,IF(EXACT("80-van fleets","80-van fleets"),IF('Model inputs'!AA14="","",'Model inputs'!AA14),IF('Model inputs'!AA27="","",'Model inputs'!AA27))) -> 0 | C13: ='Fleet growth and revenue'!C10*IF(IF(EXACT("80-van fleets","80-van fleets"),IF('Model inputs'!AA14="","",'Model inputs'!AA14),IF('Model inputs'!AA27="","",'Model inputs'!AA27))="",0,IF(EXACT("80-van fleets","80-van fleets"),IF('Model inputs'!AA14="","",'Model inputs'!AA14),IF('Model inputs'!AA27="","",'Model inputs'!AA27))) -> 0 | D13: ='Fleet growth and revenue'!D10*IF(IF(EXACT("80-van fleets","80-van fleets"),IF('Model inputs'!AA14="","",'Model inputs'!AA14),IF('Model inputs'!AA27="","",'Model inputs'!AA27))="",0,IF(EXACT("80-van fleets","80-van fleets"),IF('Model inputs'!AA14="","",'Model inputs'!AA14),IF('Model inputs'!AA27="","",'Model inputs'!AA27))) -> 0 | E13: ='Fleet growth and revenue'!E10*IF(IF(EXACT("80-van fleets","80-van fleets"),IF('Model inputs'!AA14="","",'Model inputs'!AA14),IF('Model inputs'!AA27="","",'Model inputs'!AA27))="",0,IF(EXACT("80-van fleets","80-van fleets"),IF('Model inputs'!AA14="","",'Model inputs'!AA14),IF('Model inputs'!AA27="","",'Model inputs'!AA27))) -> 0 | F13: ='Fleet growth and revenue'!F10*IF(IF(EXACT("80-van fleets","80-van fleets"),IF('Model inputs'!AA14="","",'Model inputs'!AA14),IF('Model inputs'!AA27="","",'Model inputs'!AA27))="",0,IF(EXACT("80-van fleets","80-van fleets"),IF('Model inputs'!AA14="","",'Model inputs'!AA14),IF('Model inputs'!AA27="","",'Model inputs'!AA27))) -> 0 | G13: ='Fleet growth and revenue'!G10*IF(IF(EXACT("80-van fleets","80-van fleets"),IF('Model inputs'!AA14="","",'Model inputs'!AA14),IF('Model inputs'!AA27="","",'Model inputs'!AA27))="",0,IF(EXACT("80-van fleets","80-van fleets"),IF('Model inputs'!AA14="","",'Model inputs'!AA14),IF('Model inputs'!AA27="","",'Model inputs'!AA27))) -> 160 | H13: ='Fleet growth and revenue'!H10*IF(IF(EXACT("80-van fleets","80-van fleets"),IF('Model inputs'!AA14="","",'Model inputs'!AA14),IF('Model inputs'!AA27="","",'Model inputs'!AA27))="",0,IF(EXACT("80-van fleets","80-van fleets"),IF('Model inputs'!AA14="","",'Model inputs'!AA14),IF('Model inputs'!AA27="","",'Model inputs'!AA27))) -> 160 | I13: ='Fleet growth and revenue'!I10*IF(IF(EXACT("80-van fleets","80-van fleets"),IF('Model inputs'!AA14="","",'Model inputs'!AA14),IF('Model inputs'!AA27="","",'Model inputs'!AA27))="",0,IF(EXACT("80-van fleets","80-van fleets"),IF('Model inputs'!AA14="","",'Model inputs'!AA14),IF('Model inputs'!AA27="","",'Model inputs'!AA27))) -> 240 | J13: ='Fleet growth and revenue'!J10*IF(IF(EXACT("80-van fleets","80-van fleets"),IF('Model inputs'!AA14="","",'Model inputs'!AA14),IF('Model inputs'!AA27="","",'Model inputs'!AA27))="",0,IF(EXACT("80-van fleets","80-van fleets"),IF('Model inputs'!AA14="","",'Model inputs'!AA14),IF('Model inputs'!AA27="","",'Model inputs'!AA27))) -> 240 | K13: ='Fleet growth and revenue'!K10*IF(IF(EXACT("80-van fleets","80-van fleets"),IF('Model inputs'!AA14="","",'Model inputs'!AA14),IF('Model inputs'!AA27="","",'Model inputs'!AA27))="",0,IF(EXACT("80-van fleets","80-van fleets"),IF('Model inputs'!AA14="","",'Model inputs'!AA14),IF('Model inputs'!AA27="","",'Model inputs'!AA27))) -> 320 | L13: ='Fleet growth and revenue'!L10*IF(IF(EXACT("80-van fleets","80-van fleets"),IF('Model inputs'!AA14="","",'Model inputs'!AA14),IF('Model inputs'!AA27="","",'Model inputs'!AA27))="",0,IF(EXACT("80-van fleets","80-van fleets"),IF('Model inputs'!AA14="","",'Model inputs'!AA14),IF('Model inputs'!AA27="","",'Model inputs'!AA27))) -> 320 | M13: ='Fleet growth and revenue'!M10*IF(IF(EXACT("80-van fleets","80-van fleets"),IF('Model inputs'!AA14="","",'Model inputs'!AA14),IF('Model inputs'!AA27="","",'Model inputs'!AA27))="",0,IF(EXACT("80-van fleets","80-van fleets"),IF('Model inputs'!AA14="","",'Model inputs'!AA14),IF('Model inputs'!AA27="","",'Model inputs'!AA27))) -> 400 | N13: ='Fleet growth and revenue'!N10*IF(IF(EXACT("80-van fleets","80-van fleets"),IF('Model inputs'!AA14="","",'Model inputs'!AA14),IF('Model inputs'!AA27="","",'Model inputs'!AA27))="",0,IF(EXACT("80-van fleets","80-van fleets"),IF('Model inputs'!AA14="","",'Model inputs'!AA14),IF('Model inputs'!AA27="","",'Model inputs'!AA27))) -> 400 | O13: ='Fleet growth and revenue'!O10*IF(IF(EXACT("80-van fleets","80-van fleets"),IF('Model inputs'!AA14="","",'Model inputs'!AA14),IF('Model inputs'!AA27="","",'Model inputs'!AA27))="",0,IF(EXACT("80-van fleets","80-van fleets"),IF('Model inputs'!AA14="","",'Model inputs'!AA14),IF('Model inputs'!AA27="","",'Model inputs'!AA27))) -> 480 | P13: ='Fleet growth and revenue'!P10*IF(IF(EXACT("80-van fleets","80-van fleets"),IF('Model inputs'!AA14="","",'Model inputs'!AA14),IF('Model inputs'!AA27="","",'Model inputs'!AA27))="",0,IF(EXACT("80-van fleets","80-van fleets"),IF('Model inputs'!AA14="","",'Model inputs'!AA14),IF('Model inputs'!AA27="","",'Model inputs'!AA27))) -> 560 | Q13: ='Fleet growth and revenue'!Q10*IF(IF(EXACT("80-van fleets","80-van fleets"),IF('Model inputs'!AA14="","",'Model inputs'!AA14),IF('Model inputs'!AA27="","",'Model inputs'!AA27))="",0,IF(EXACT("80-van fleets","80-van fleets"),IF('Model inputs'!AA14="","",'Model inputs'!AA14),IF('Model inputs'!AA27="","",'Model inputs'!AA27))) -> 560 | R13: ='Fleet growth and revenue'!R10*IF(IF(EXACT("80-van fleets","80-van fleets"),IF('Model inputs'!AA14="","",'Model inputs'!AA14),IF('Model inputs'!AA27="","",'Model inputs'!AA27))="",0,IF(EXACT("80-van fleets","80-van fleets"),IF('Model inputs'!AA14="","",'Model inputs'!AA14),IF('Model inputs'!AA27="","",'Model inputs'!AA27))) -> 640 | S13: ='Fleet growth and revenue'!S10*IF(IF(EXACT("80-van fleets","80-van fleets"),IF('Model inputs'!AA14="","",'Model inputs'!AA14),IF('Model inputs'!AA27="","",'Model inputs'!AA27))="",0,IF(EXACT("80-van fleets","80-van fleets"),IF('Model inputs'!AA14="","",'Model inputs'!AA14),IF('Model inputs'!AA27="","",'Model inputs'!AA27))) -> 640 | T13: ='Fleet growth and revenue'!T10*IF(IF(EXACT("80-van fleets","80-van fleets"),IF('Model inputs'!AA14="","",'Model inputs'!AA14),IF('Model inputs'!AA27="","",'Model inputs'!AA27))="",0,IF(EXACT("80-van fleets","80-van fleets"),IF('Model inputs'!AA14="","",'Model inputs'!AA14),IF('Model inputs'!AA27="","",'Model inputs'!AA27))) -> 720 | U13: ='Fleet growth and revenue'!U10*IF(IF(EXACT("80-van fleets","80-van fleets"),IF('Model inputs'!AA14="","",'Model inputs'!AA14),IF('Model inputs'!AA27="","",'Model inputs'!AA27))="",0,IF(EXACT("80-van fleets","80-van fleets"),IF('Model inputs'!AA14="","",'Model inputs'!AA14),IF('Model inputs'!AA27="","",'Model inputs'!AA27))) -> 720 | V13: ='Fleet growth and revenue'!V10*IF(IF(EXACT("80-van fleets","80-van fleets"),IF('Model inputs'!AA14="","",'Model inputs'!AA14),IF('Model inputs'!AA27="","",'Model inputs'!AA27))="",0,IF(EXACT("80-van fleets","80-van fleets"),IF('Model inputs'!AA14="","",'Model inputs'!AA14),IF('Model inputs'!AA27="","",'Model inputs'!AA27))) -> 800 | W13: ='Fleet growth and revenue'!W10*IF(IF(EXACT("80-van fleets","80-van fleets"),IF('Model inputs'!AA14="","",'Model inputs'!AA14),IF('Model inputs'!AA27="","",'Model inputs'!AA27))="",0,IF(EXACT("80-van fleets","80-van fleets"),IF('Model inputs'!AA14="","",'Model inputs'!AA14),IF('Model inputs'!AA27="","",'Model inputs'!AA27))) -> 800 | X13: ='Fleet growth and revenue'!X10*IF(IF(EXACT("80-van fleets","80-van fleets"),IF('Model inputs'!AA14="","",'Model inputs'!AA14),IF('Model inputs'!AA27="","",'Model inputs'!AA27))="",0,IF(EXACT("80-van fleets","80-van fleets"),IF('Model inputs'!AA14="","",'Model inputs'!AA14),IF('Model inputs'!AA27="","",'Model inputs'!AA27))) -> 880 | Y13: ='Fleet growth and revenue'!Y10*IF(IF(EXACT("80-van fleets","80-van fleets"),IF('Model inputs'!AA14="","",'Model inputs'!AA14),IF('Model inputs'!AA27="","",'Model inputs'!AA27))="",0,IF(EXACT("80-van fleets","80-van fleets"),IF('Model inputs'!AA14="","",'Model inputs'!AA14),IF('Model inputs'!AA27="","",'Model inputs'!AA27))) -> 880
A14: Churned fleets | B14: =IF(IF(IF(ISERROR('Fleet growth and revenue'!B5=1),'Fleet growth and revenue'!B5=1,IF('Fleet growth and revenue'!B5="","",'Fleet growth and revenue'!B5=1))="",FALSE,IF(ISERROR('Fleet growth and revenue'!B5=1),'Fleet growth and revenue'!B5=1,IF('Fleet growth and revenue'!B5="","",'Fleet growth and revenue'!B5=1))),0,'Model inputs'!B6*'Model inputs'!AA20) -> 0 | C14: =IF(IF(IF(ISERROR('Fleet growth and revenue'!C5=1),'Fleet growth and revenue'!C5=1,IF('Fleet growth and revenue'!C5="","",'Fleet growth and revenue'!C5=1))="",FALSE,IF(ISERROR('Fleet growth and revenue'!C5=1),'Fleet growth and revenue'!C5=1,IF('Fleet growth and revenue'!C5="","",'Fleet growth and revenue'!C5=1))),0,'Fleet growth and revenue'!B6*'Model inputs'!AA20) -> 0 | D14: =IF(IF(IF(ISERROR('Fleet growth and revenue'!D5=1),'Fleet growth and revenue'!D5=1,IF('Fleet growth and revenue'!D5="","",'Fleet growth and revenue'!D5=1))="",FALSE,IF(ISERROR('Fleet growth and revenue'!D5=1),'Fleet growth and revenue'!D5=1,IF('Fleet growth and revenue'!D5="","",'Fleet growth and revenue'!D5=1))),0,'Fleet growth and revenue'!C6*'Model inputs'!AA20) -> 0 | E14: =IF(IF(IF(ISERROR('Fleet growth and revenue'!E5=1),'Fleet growth and revenue'!E5=1,IF('Fleet growth and revenue'!E5="","",'Fleet growth and revenue'!E5=1))="",FALSE,IF(ISERROR('Fleet growth and revenue'!E5=1),'Fleet growth and revenue'!E5=1,IF('Fleet growth and revenue'!E5="","",'Fleet growth and revenue'!E5=1))),0,'Fleet growth and revenue'!D6*'Model inputs'!AA20) -> 0.03 | F14: =IF(IF(IF(ISERROR('Fleet growth and revenue'!F5=1),'Fleet growth and revenue'!F5=1,IF('Fleet growth and revenue'!F5="","",'Fleet growth and revenue'!F5=1))="",FALSE,IF(ISERROR('Fleet growth and revenue'!F5=1),'Fleet growth and revenue'!F5=1,IF('Fleet growth and revenue'!F5="","",'Fleet growth and revenue'!F5=1))),0,'Fleet growth and revenue'!E6*'Model inputs'!AA20) -> 0.06 | G14: =IF(IF(IF(ISERROR('Fleet growth and revenue'!G5=1),'Fleet growth and revenue'!G5=1,IF('Fleet growth and revenue'!G5="","",'Fleet growth and revenue'!G5=1))="",FALSE,IF(ISERROR('Fleet growth and revenue'!G5=1),'Fleet growth and revenue'!G5=1,IF('Fleet growth and revenue'!G5="","",'Fleet growth and revenue'!G5=1))),0,'Fleet growth and revenue'!F6*'Model inputs'!AA20) -> 0.08 | H14: =IF(IF(IF(ISERROR('Fleet growth and revenue'!H5=1),'Fleet growth and revenue'!H5=1,IF('Fleet growth and revenue'!H5="","",'Fleet growth and revenue'!H5=1))="",FALSE,IF(ISERROR('Fleet growth and revenue'!H5=1),'Fleet growth and revenue'!H5=1,IF('Fleet growth and revenue'!H5="","",'Fleet growth and revenue'!H5=1))),0,'Fleet growth and revenue'!G6*'Model inputs'!AA20) -> 0.11 | I14: =IF(IF(IF(ISERROR('Fleet growth and revenue'!I5=1),'Fleet growth and revenue'!I5=1,IF('Fleet growth and revenue'!I5="","",'Fleet growth and revenue'!I5=1))="",FALSE,IF(ISERROR('Fleet growth and revenue'!I5=1),'Fleet growth and revenue'!I5=1,IF('Fleet growth and revenue'!I5="","",'Fleet growth and revenue'!I5=1))),0,'Fleet growth and revenue'!H6*'Model inputs'!AA20) -> 0.14 | J14: =IF(IF(IF(ISERROR('Fleet growth and revenue'!J5=1),'Fleet growth and revenue'!J5=1,IF('Fleet growth and revenue'!J5="","",'Fleet growth and revenue'!J5=1))="",FALSE,IF(ISERROR('Fleet growth and revenue'!J5=1),'Fleet growth and revenue'!J5=1,IF('Fleet growth and revenue'!J5="","",'Fleet growth and revenue'!J5=1))),0,'Fleet growth and revenue'!I6*'Model inputs'!AA20) -> 0.17 | K14: =IF(IF(IF(ISERROR('Fleet growth and revenue'!K5=1),'Fleet growth and revenue'!K5=1,IF('Fleet growth and revenue'!K5="","",'Fleet growth and revenue'!K5=1))="",FALSE,IF(ISERROR('Fleet growth and revenue'!K5=1),'Fleet growth and revenue'!K5=1,IF('Fleet growth and revenue'!K5="","",'Fleet growth and revenue'!K5=1))),0,'Fleet growth and revenue'!J6*'Model inputs'!AA20) -> 0.19 | L14: =IF(IF(IF(ISERROR('Fleet growth and revenue'!L5=1),'Fleet growth and revenue'!L5=1,IF('Fleet growth and revenue'!L5="","",'Fleet growth and revenue'!L5=1))="",FALSE,IF(ISERROR('Fleet growth and revenue'!L5=1),'Fleet growth and revenue'!L5=1,IF('Fleet growth and revenue'!L5="","",'Fleet growth and revenue'!L5=1))),0,'Fleet growth and revenue'!K6*'Model inputs'!AA20) -> 0.22 | M14: =IF(IF(IF(ISERROR('Fleet growth and revenue'!M5=1),'Fleet growth and revenue'!M5=1,IF('Fleet growth and revenue'!M5="","",'Fleet growth and revenue'!M5=1))="",FALSE,IF(ISERROR('Fleet growth and revenue'!M5=1),'Fleet growth and revenue'!M5=1,IF('Fleet growth and revenue'!M5="","",'Fleet growth and revenue'!M5=1))),0,'Fleet growth and revenue'!L6*'Model inputs'!AA20) -> 0.25 | N14: =IF(IF(IF(ISERROR('Fleet growth and revenue'!N5=1),'Fleet growth and revenue'!N5=1,IF('Fleet growth and revenue'!N5="","",'Fleet growth and revenue'!N5=1))="",FALSE,IF(ISERROR('Fleet growth and revenue'!N5=1),'Fleet growth and revenue'!N5=1,IF('Fleet growth and revenue'!N5="","",'Fleet growth and revenue'!N5=1))),0,'Fleet growth and revenue'!M6*'Model inputs'!AA20) -> 0.27 | O14: =IF(IF(IF(ISERROR('Fleet growth and revenue'!O5=1),'Fleet growth and revenue'!O5=1,IF('Fleet growth and revenue'!O5="","",'Fleet growth and revenue'!O5=1))="",FALSE,IF(ISERROR('Fleet growth and revenue'!O5=1),'Fleet growth and revenue'!O5=1,IF('Fleet growth and revenue'!O5="","",'Fleet growth and revenue'!O5=1))),0,'Fleet growth and revenue'!N6*'Model inputs'!AA20) -> 0.3 | P14: =IF(IF(IF(ISERROR('Fleet growth and revenue'!P5=1),'Fleet growth and revenue'!P5=1,IF('Fleet growth and revenue'!P5="","",'Fleet growth and revenue'!P5=1))="",FALSE,IF(ISERROR('Fleet growth and revenue'!P5=1),'Fleet growth and revenue'!P5=1,IF('Fleet growth and revenue'!P5="","",'Fleet growth and revenue'!P5=1))),0,'Fleet growth and revenue'!O6*'Model inputs'!AA20) -> 0.33 | Q14: =IF(IF(IF(ISERROR('Fleet growth and revenue'!Q5=1),'Fleet growth and revenue'!Q5=1,IF('Fleet growth and revenue'!Q5="","",'Fleet growth and revenue'!Q5=1))="",FALSE,IF(ISERROR('Fleet growth and revenue'!Q5=1),'Fleet growth and revenue'!Q5=1,IF('Fleet growth and revenue'!Q5="","",'Fleet growth and revenue'!Q5=1))),0,'Fleet growth and revenue'!P6*'Model inputs'!AA20) -> 0.36 | R14: =IF(IF(IF(ISERROR('Fleet growth and revenue'!R5=1),'Fleet growth and revenue'!R5=1,IF('Fleet growth and revenue'!R5="","",'Fleet growth and revenue'!R5=1))="",FALSE,IF(ISERROR('Fleet growth and revenue'!R5=1),'Fleet growth and revenue'!R5=1,IF('Fleet growth and revenue'!R5="","",'Fleet growth and revenue'!R5=1))),0,'Fleet growth and revenue'!Q6*'Model inputs'!AA20) -> 0.38 | S14: =IF(IF(IF(ISERROR('Fleet growth and revenue'!S5=1),'Fleet growth and revenue'!S5=1,IF('Fleet growth and revenue'!S5="","",'Fleet growth and revenue'!S5=1))="",FALSE,IF(ISERROR('Fleet growth and revenue'!S5=1),'Fleet growth and revenue'!S5=1,IF('Fleet growth and revenue'!S5="","",'Fleet growth and revenue'!S5=1))),0,'Fleet growth and revenue'!R6*'Model inputs'!AA20) -> 0.41 | T14: =IF(IF(IF(ISERROR('Fleet growth and revenue'!T5=1),'Fleet growth and revenue'!T5=1,IF('Fleet growth and revenue'!T5="","",'Fleet growth and revenue'!T5=1))="",FALSE,IF(ISERROR('Fleet growth and revenue'!T5=1),'Fleet growth and revenue'!T5=1,IF('Fleet growth and revenue'!T5="","",'Fleet growth and revenue'!T5=1))),0,'Fleet growth and revenue'!S6*'Model inputs'!AA20) -> 0.44 | U14: =IF(IF(IF(ISERROR('Fleet growth and revenue'!U5=1),'Fleet growth and revenue'!U5=1,IF('Fleet growth and revenue'!U5="","",'Fleet growth and revenue'!U5=1))="",FALSE,IF(ISERROR('Fleet growth and revenue'!U5=1),'Fleet growth and revenue'!U5=1,IF('Fleet growth and revenue'!U5="","",'Fleet growth and revenue'!U5=1))),0,'Fleet growth and revenue'!T6*'Model inputs'!AA20) -> 0.46 | V14: =IF(IF(IF(ISERROR('Fleet growth and revenue'!V5=1),'Fleet growth and revenue'!V5=1,IF('Fleet growth and revenue'!V5="","",'Fleet growth and revenue'!V5=1))="",FALSE,IF(ISERROR('Fleet growth and revenue'!V5=1),'Fleet growth and revenue'!V5=1,IF('Fleet growth and revenue'!V5="","",'Fleet growth and revenue'!V5=1))),0,'Fleet growth and revenue'!U6*'Model inputs'!AA20) -> 0.49 | W14: =IF(IF(IF(ISERROR('Fleet growth and revenue'!W5=1),'Fleet growth and revenue'!W5=1,IF('Fleet growth and revenue'!W5="","",'Fleet growth and revenue'!W5=1))="",FALSE,IF(ISERROR('Fleet growth and revenue'!W5=1),'Fleet growth and revenue'!W5=1,IF('Fleet growth and revenue'!W5="","",'Fleet growth and revenue'!W5=1))),0,'Fleet growth and revenue'!V6*'Model inputs'!AA20) -> 0.52 | X14: =IF(IF(IF(ISERROR('Fleet growth and revenue'!X5=1),'Fleet growth and revenue'!X5=1,IF('Fleet growth and revenue'!X5="","",'Fleet growth and revenue'!X5=1))="",FALSE,IF(ISERROR('Fleet growth and revenue'!X5=1),'Fleet growth and revenue'!X5=1,IF('Fleet growth and revenue'!X5="","",'Fleet growth and revenue'!X5=1))),0,'Fleet growth and revenue'!W6*'Model inputs'!AA20) -> 0.55 | Y14: =IF(IF(IF(ISERROR('Fleet growth and revenue'!Y5=1),'Fleet growth and revenue'!Y5=1,IF('Fleet growth and revenue'!Y5="","",'Fleet growth and revenue'!Y5=1))="",FALSE,IF(ISERROR('Fleet growth and revenue'!Y5=1),'Fleet growth and revenue'!Y5=1,IF('Fleet growth and revenue'!Y5="","",'Fleet growth and revenue'!Y5=1))),0,'Fleet growth and revenue'!X6*'Model inputs'!AA20) -> 0.57
A15: Gross fleet wins required | B15: =MAX(0,'Fleet growth and revenue'!B6-IF(IF(IF(IF(ISERROR('Fleet growth and revenue'!B5=1),'Fleet growth and revenue'!B5=1,IF('Fleet growth and revenue'!B5="","",'Fleet growth and revenue'!B5=1))="",FALSE,IF(ISERROR('Fleet growth and revenue'!B5=1),'Fleet growth and revenue'!B5=1,IF('Fleet growth and revenue'!B5="","",'Fleet growth and revenue'!B5=1))),0,IF('Model inputs'!B6="","",'Model inputs'!B6))="",0,IF(IF(IF(ISERROR('Fleet growth and revenue'!B5=1),'Fleet growth and revenue'!B5=1,IF('Fleet growth and revenue'!B5="","",'Fleet growth and revenue'!B5=1))="",FALSE,IF(ISERROR('Fleet growth and revenue'!B5=1),'Fleet growth and revenue'!B5=1,IF('Fleet growth and revenue'!B5="","",'Fleet growth and revenue'!B5=1))),0,IF('Model inputs'!B6="","",'Model inputs'!B6)))+'Fleet growth and revenue'!B14) -> 0 | C15: =MAX(0,'Fleet growth and revenue'!C6-IF(IF(IF(IF(ISERROR('Fleet growth and revenue'!C5=1),'Fleet growth and revenue'!C5=1,IF('Fleet growth and revenue'!C5="","",'Fleet growth and revenue'!C5=1))="",FALSE,IF(ISERROR('Fleet growth and revenue'!C5=1),'Fleet growth and revenue'!C5=1,IF('Fleet growth and revenue'!C5="","",'Fleet growth and revenue'!C5=1))),0,IF('Fleet growth and revenue'!B6="","",'Fleet growth and revenue'!B6))="",0,IF(IF(IF(ISERROR('Fleet growth and revenue'!C5=1),'Fleet growth and revenue'!C5=1,IF('Fleet growth and revenue'!C5="","",'Fleet growth and revenue'!C5=1))="",FALSE,IF(ISERROR('Fleet growth and revenue'!C5=1),'Fleet growth and revenue'!C5=1,IF('Fleet growth and revenue'!C5="","",'Fleet growth and revenue'!C5=1))),0,IF('Fleet growth and revenue'!B6="","",'Fleet growth and revenue'!B6)))+'Fleet growth and revenue'!C14) -> 0 | D15: =MAX(0,'Fleet growth and revenue'!D6-IF(IF(IF(IF(ISERROR('Fleet growth and revenue'!D5=1),'Fleet growth and revenue'!D5=1,IF('Fleet growth and revenue'!D5="","",'Fleet growth and revenue'!D5=1))="",FALSE,IF(ISERROR('Fleet growth and revenue'!D5=1),'Fleet growth and revenue'!D5=1,IF('Fleet growth and revenue'!D5="","",'Fleet growth and revenue'!D5=1))),0,IF('Fleet growth and revenue'!C6="","",'Fleet growth and revenue'!C6))="",0,IF(IF(IF(ISERROR('Fleet growth and revenue'!D5=1),'Fleet growth and revenue'!D5=1,IF('Fleet growth and revenue'!D5="","",'Fleet growth and revenue'!D5=1))="",FALSE,IF(ISERROR('Fleet growth and revenue'!D5=1),'Fleet growth and revenue'!D5=1,IF('Fleet growth and revenue'!D5="","",'Fleet growth and revenue'!D5=1))),0,IF('Fleet growth and revenue'!C6="","",'Fleet growth and revenue'!C6)))+'Fleet growth and revenue'!D14) -> 3 | E15: =MAX(0,'Fleet growth and revenue'!E6-IF(IF(IF(IF(ISERROR('Fleet growth and revenue'!E5=1),'Fleet growth and revenue'!E5=1,IF('Fleet growth and revenue'!E5="","",'Fleet growth and revenue'!E5=1))="",FALSE,IF(ISERROR('Fleet growth and revenue'!E5=1),'Fleet growth and revenue'!E5=1,IF('Fleet growth and revenue'!E5="","",'Fleet growth and revenue'!E5=1))),0,IF('Fleet growth and revenue'!D6="","",'Fleet growth and revenue'!D6))="",0,IF(IF(IF(ISERROR('Fleet growth and revenue'!E5=1),'Fleet growth and revenue'!E5=1,IF('Fleet growth and revenue'!E5="","",'Fleet growth and revenue'!E5=1))="",FALSE,IF(ISERROR('Fleet growth and revenue'!E5=1),'Fleet growth and revenue'!E5=1,IF('Fleet growth and revenue'!E5="","",'Fleet growth and revenue'!E5=1))),0,IF('Fleet growth and revenue'!D6="","",'Fleet growth and revenue'!D6)))+'Fleet growth and revenue'!E14) -> 3.03 | F15: =MAX(0,'Fleet growth and revenue'!F6-IF(IF(IF(IF(ISERROR('Fleet growth and revenue'!F5=1),'Fleet growth and revenue'!F5=1,IF('Fleet growth and revenue'!F5="","",'Fleet growth and revenue'!F5=1))="",FALSE,IF(ISERROR('Fleet growth and revenue'!F5=1),'Fleet growth and revenue'!F5=1,IF('Fleet growth and revenue'!F5="","",'Fleet growth and revenue'!F5=1))),0,IF('Fleet growth and revenue'!E6="","",'Fleet growth and revenue'!E6))="",0,IF(IF(IF(ISERROR('Fleet growth and revenue'!F5=1),'Fleet growth and revenue'!F5=1,IF('Fleet growth and revenue'!F5="","",'Fleet growth and revenue'!F5=1))="",FALSE,IF(ISERROR('Fleet growth and revenue'!F5=1),'Fleet growth and revenue'!F5=1,IF('Fleet growth and revenue'!F5="","",'Fleet growth and revenue'!F5=1))),0,IF('Fleet growth and revenue'!E6="","",'Fleet growth and revenue'!E6)))+'Fleet growth and revenue'!F14) -> 2.06 | G15: =MAX(0,'Fleet growth and revenue'!G6-IF(IF(IF(IF(ISERROR('Fleet growth and revenue'!G5=1),'Fleet growth and revenue'!G5=1,IF('Fleet growth and revenue'!G5="","",'Fleet growth and revenue'!G5=1))="",FALSE,IF(ISERROR('Fleet growth and revenue'!G5=1),'Fleet growth and revenue'!G5=1,IF('Fleet growth and revenue'!G5="","",'Fleet growth and revenue'!G5=1))),0,IF('Fleet growth and revenue'!F6="","",'Fleet growth and revenue'!F6))="",0,IF(IF(IF(ISERROR('Fleet growth and revenue'!G5=1),'Fleet growth and revenue'!G5=1,IF('Fleet growth and revenue'!G5="","",'Fleet growth and revenue'!G5=1))="",FALSE,IF(ISERROR('Fleet growth and revenue'!G5=1),'Fleet growth and revenue'!G5=1,IF('Fleet growth and revenue'!G5="","",'Fleet growth and revenue'!G5=1))),0,IF('Fleet growth and revenue'!F6="","",'Fleet growth and revenue'!F6)))+'Fleet growth and revenue'!G14) -> 3.08 | H15: =MAX(0,'Fleet growth and revenue'!H6-IF(IF(IF(IF(ISERROR('Fleet growth and revenue'!H5=1),'Fleet growth and revenue'!H5=1,IF('Fleet growth and revenue'!H5="","",'Fleet growth and revenue'!H5=1))="",FALSE,IF(ISERROR('Fleet growth and revenue'!H5=1),'Fleet growth and revenue'!H5=1,IF('Fleet growth and revenue'!H5="","",'Fleet growth and revenue'!H5=1))),0,IF('Fleet growth and revenue'!G6="","",'Fleet growth and revenue'!G6))="",0,IF(IF(IF(ISERROR('Fleet growth and revenue'!H5=1),'Fleet growth and revenue'!H5=1,IF('Fleet growth and revenue'!H5="","",'Fleet growth and revenue'!H5=1))="",FALSE,IF(ISERROR('Fleet growth and revenue'!H5=1),'Fleet growth and revenue'!H5=1,IF('Fleet growth and revenue'!H5="","",'Fleet growth and revenue'!H5=1))),0,IF('Fleet growth and revenue'!G6="","",'Fleet growth and revenue'!G6)))+'Fleet growth and revenue'!H14) -> 3.11 | I15: =MAX(0,'Fleet growth and revenue'!I6-IF(IF(IF(IF(ISERROR('Fleet growth and revenue'!I5=1),'Fleet growth and revenue'!I5=1,IF('Fleet growth and revenue'!I5="","",'Fleet growth and revenue'!I5=1))="",FALSE,IF(ISERROR('Fleet growth and revenue'!I5=1),'Fleet growth and revenue'!I5=1,IF('Fleet growth and revenue'!I5="","",'Fleet growth and revenue'!I5=1))),0,IF('Fleet growth and revenue'!H6="","",'Fleet growth and revenue'!H6))="",0,IF(IF(IF(ISERROR('Fleet growth and revenue'!I5=1),'Fleet growth and revenue'!I5=1,IF('Fleet growth and revenue'!I5="","",'Fleet growth and revenue'!I5=1))="",FALSE,IF(ISERROR('Fleet growth and revenue'!I5=1),'Fleet growth and revenue'!I5=1,IF('Fleet growth and revenue'!I5="","",'Fleet growth and revenue'!I5=1))),0,IF('Fleet growth and revenue'!H6="","",'Fleet growth and revenue'!H6)))+'Fleet growth and revenue'!I14) -> 3.14 | J15: =MAX(0,'Fleet growth and revenue'!J6-IF(IF(IF(IF(ISERROR('Fleet growth and revenue'!J5=1),'Fleet growth and revenue'!J5=1,IF('Fleet growth and revenue'!J5="","",'Fleet growth and revenue'!J5=1))="",FALSE,IF(ISERROR('Fleet growth and revenue'!J5=1),'Fleet growth and revenue'!J5=1,IF('Fleet growth and revenue'!J5="","",'Fleet growth and revenue'!J5=1))),0,IF('Fleet growth and revenue'!I6="","",'Fleet growth and revenue'!I6))="",0,IF(IF(IF(ISERROR('Fleet growth and revenue'!J5=1),'Fleet growth and revenue'!J5=1,IF('Fleet growth and revenue'!J5="","",'Fleet growth and revenue'!J5=1))="",FALSE,IF(ISERROR('Fleet growth and revenue'!J5=1),'Fleet growth and revenue'!J5=1,IF('Fleet growth and revenue'!J5="","",'Fleet growth and revenue'!J5=1))),0,IF('Fleet growth and revenue'!I6="","",'Fleet growth and revenue'!I6)))+'Fleet growth and revenue'!J14) -> 2.17 | ... Y15: =MAX(0,'Fleet growth and revenue'!Y6-IF(IF(IF(IF(ISERROR('Fleet growth and revenue'!Y5=1),'Fleet growth and revenue'!Y5=1,IF('Fleet growth and revenue'!Y5="","",'Fleet growth and revenue'!Y5=1))="",FALSE,IF(ISERROR('Fleet growth and revenue'!Y5=1),'Fleet growth and revenue'!Y5=1,IF('Fleet growth and revenue'!Y5="","",'Fleet growth and revenue'!Y5=1))),0,IF('Fleet growth and revenue'!X6="","",'Fleet growth and revenue'!X6))="",0,IF(IF(IF(ISERROR('Fleet growth and revenue'!Y5=1),'Fleet growth and revenue'!Y5=1,IF('Fleet growth and revenue'!Y5="","",'Fleet growth and revenue'!Y5=1))="",FALSE,IF(ISERROR('Fleet growth and revenue'!Y5=1),'Fleet growth and revenue'!Y5=1,IF('Fleet growth and revenue'!Y5="","",'Fleet growth and revenue'!Y5=1))),0,IF('Fleet growth and revenue'!X6="","",'Fleet growth and revenue'!X6)))+'Fleet growth and revenue'!Y14) -> 3.57
A16: Van subscription revenue | B16: =SUM('Fleet growth and revenue'!B17,'Fleet growth and revenue'!B18) -> 0 | C16: =SUM('Fleet growth and revenue'!C17,'Fleet growth and revenue'!C18) -> 0 | D16: =SUM('Fleet growth and revenue'!D17,'Fleet growth and revenue'!D18) -> 4410 | E16: =SUM('Fleet growth and revenue'!E17,'Fleet growth and revenue'!E18) -> 8820 | F16: =SUM('Fleet growth and revenue'!F17,'Fleet growth and revenue'!F18) -> 11760 | G16: =SUM('Fleet growth and revenue'!G17,'Fleet growth and revenue'!G18) -> 21070 | H16: =SUM('Fleet growth and revenue'!H17,'Fleet growth and revenue'!H18) -> 25480 | I16: =SUM('Fleet growth and revenue'!I17,'Fleet growth and revenue'!I18) -> 32340 | ... Y16: =SUM('Fleet growth and revenue'!Y17,'Fleet growth and revenue'!Y18) -> 115150
A17: 30-van fleets | B17: ='Fleet growth and revenue'!B12*'Model inputs'!AA28 -> 0 | C17: ='Fleet growth and revenue'!C12*'Model inputs'!AA28 -> 0 | D17: ='Fleet growth and revenue'!D12*'Model inputs'!AA28 -> 4410 | E17: ='Fleet growth and revenue'!E12*'Model inputs'!AA28 -> 8820 | F17: ='Fleet growth and revenue'!F12*'Model inputs'!AA28 -> 11760 | G17: ='Fleet growth and revenue'!G12*'Model inputs'!AA28 -> 13230 | H17: ='Fleet growth and revenue'!H12*'Model inputs'!AA28 -> 17640 | I17: ='Fleet growth and revenue'!I12*'Model inputs'!AA28 -> 20580 | J17: ='Fleet growth and revenue'!J12*'Model inputs'!AA28 -> 23520 | K17: ='Fleet growth and revenue'!K12*'Model inputs'!AA28 -> 26460 | L17: ='Fleet growth and revenue'!L12*'Model inputs'!AA28 -> 30870 | M17: ='Fleet growth and revenue'!M12*'Model inputs'!AA28 -> 32340 | N17: ='Fleet growth and revenue'!N12*'Model inputs'!AA28 -> 36750 | O17: ='Fleet growth and revenue'!O12*'Model inputs'!AA28 -> 39690 | P17: ='Fleet growth and revenue'!P12*'Model inputs'!AA28 -> 42630 | Q17: ='Fleet growth and revenue'!Q12*'Model inputs'!AA28 -> 45570 | R17: ='Fleet growth and revenue'!R12*'Model inputs'!AA28 -> 48510 | S17: ='Fleet growth and revenue'!S12*'Model inputs'!AA28 -> 52920 | T17: ='Fleet growth and revenue'!T12*'Model inputs'!AA28 -> 54390 | U17: ='Fleet growth and revenue'!U12*'Model inputs'!AA28 -> 58800 | V17: ='Fleet growth and revenue'!V12*'Model inputs'!AA28 -> 61740 | W17: ='Fleet growth and revenue'!W12*'Model inputs'!AA28 -> 66150 | X17: ='Fleet growth and revenue'!X12*'Model inputs'!AA28 -> 67620 | Y17: ='Fleet growth and revenue'!Y12*'Model inputs'!AA28 -> 72030
A18: 80-van fleets | B18: ='Fleet growth and revenue'!B13*'Model inputs'!AA28 -> 0 | C18: ='Fleet growth and revenue'!C13*'Model inputs'!AA28 -> 0 | D18: ='Fleet growth and revenue'!D13*'Model inputs'!AA28 -> 0 | E18: ='Fleet growth and revenue'!E13*'Model inputs'!AA28 -> 0 | F18: ='Fleet growth and revenue'!F13*'Model inputs'!AA28 -> 0 | G18: ='Fleet growth and revenue'!G13*'Model inputs'!AA28 -> 7840 | H18: ='Fleet growth and revenue'!H13*'Model inputs'!AA28 -> 7840 | I18: ='Fleet growth and revenue'!I13*'Model inputs'!AA28 -> 11760 | J18: ='Fleet growth and revenue'!J13*'Model inputs'!AA28 -> 11760 | K18: ='Fleet growth and revenue'!K13*'Model inputs'!AA28 -> 15680 | L18: ='Fleet growth and revenue'!L13*'Model inputs'!AA28 -> 15680 | M18: ='Fleet growth and revenue'!M13*'Model inputs'!AA28 -> 19600 | N18: ='Fleet growth and revenue'!N13*'Model inputs'!AA28 -> 19600 | O18: ='Fleet growth and revenue'!O13*'Model inputs'!AA28 -> 23520 | P18: ='Fleet growth and revenue'!P13*'Model inputs'!AA28 -> 27440 | Q18: ='Fleet growth and revenue'!Q13*'Model inputs'!AA28 -> 27440 | R18: ='Fleet growth and revenue'!R13*'Model inputs'!AA28 -> 31360 | S18: ='Fleet growth and revenue'!S13*'Model inputs'!AA28 -> 31360 | T18: ='Fleet growth and revenue'!T13*'Model inputs'!AA28 -> 35280 | U18: ='Fleet growth and revenue'!U13*'Model inputs'!AA28 -> 35280 | V18: ='Fleet growth and revenue'!V13*'Model inputs'!AA28 -> 39200 | W18: ='Fleet growth and revenue'!W13*'Model inputs'!AA28 -> 39200 | X18: ='Fleet growth and revenue'!X13*'Model inputs'!AA28 -> 43120 | Y18: ='Fleet growth and revenue'!Y13*'Model inputs'!AA28 -> 43120
A19: Platform fee revenue | B19: =SUM('Fleet growth and revenue'!B20,'Fleet growth and revenue'!B21) -> 0 | C19: =SUM('Fleet growth and revenue'!C20,'Fleet growth and revenue'!C21) -> 0 | D19: =SUM('Fleet growth and revenue'!D20,'Fleet growth and revenue'!D21) -> 0 | E19: =SUM('Fleet growth and revenue'!E20,'Fleet growth and revenue'!E21) -> 0 | F19: =SUM('Fleet growth and revenue'!F20,'Fleet growth and revenue'!F21) -> 0 | G19: =SUM('Fleet growth and revenue'!G20,'Fleet growth and revenue'!G21) -> 1000 | H19: =SUM('Fleet growth and revenue'!H20,'Fleet growth and revenue'!H21) -> 1000 | I19: =SUM('Fleet growth and revenue'!I20,'Fleet growth and revenue'!I21) -> 1500 | ... Y19: =SUM('Fleet growth and revenue'!Y20,'Fleet growth and revenue'!Y21) -> 5500
A20: 30-van fleets | B20: ='Fleet growth and revenue'!B9*IF(IF(IF(IF(ISERROR(IF(EXACT("30-van fleets","80-van fleets"),IF('Model inputs'!AA14="","",'Model inputs'!AA14),IF('Model inputs'!AA27="","",'Model inputs'!AA27))>'Model inputs'!AA24),IF(EXACT("30-van fleets","80-van fleets"),IF('Model inputs'!AA14="","",'Model inputs'!AA14),IF('Model inputs'!AA27="","",'Model inputs'!AA27))>'Model inputs'!AA24,IF(OR(IF(EXACT("30-van fleets","80-van fleets"),IF('Model inputs'!AA14="","",'Model inputs'!AA14),IF('Model inputs'!AA27="","",'Model inputs'!AA27))="",'Model inputs'!AA24=""),"",IF(EXACT("30-van fleets","80-van fleets"),IF('Model inputs'!AA14="","",'Model inputs'!AA14),IF('Model inputs'!AA27="","",'Model inputs'!AA27))>'Model inputs'!AA24))="",FALSE,IF(ISERROR(IF(EXACT("30-van fleets","80-van fleets"),IF('Model inputs'!AA14="","",'Model inputs'!AA14),IF('Model inputs'!AA27="","",'Model inputs'!AA27))>'Model inputs'!AA24),IF(EXACT("30-van fleets","80-van fleets"),IF('Model inputs'!AA14="","",'Model inputs'!AA14),IF('Model inputs'!AA27="","",'Model inputs'!AA27))>'Model inputs'!AA24,IF(OR(IF(EXACT("30-van fleets","80-van fleets"),IF('Model inputs'!AA14="","",'Model inputs'!AA14),IF('Model inputs'!AA27="","",'Model inputs'!AA27))="",'Model inputs'!AA24=""),"",IF(EXACT("30-van fleets","80-van fleets"),IF('Model inputs'!AA14="","",'Model inputs'!AA14),IF('Model inputs'!AA27="","",'Model inputs'!AA27))>'Model inputs'!AA24))),IF('Model inputs'!AA11="","",'Model inputs'!AA11),0)="",0,IF(IF(IF(ISERROR(IF(EXACT("30-van fleets","80-van fleets"),IF('Model inputs'!AA14="","",'Model inputs'!AA14),IF('Model inputs'!AA27="","",'Model inputs'!AA27))>'Model inputs'!AA24),IF(EXACT("30-van fleets","80-van fleets"),IF('Model inputs'!AA14="","",'Model inputs'!AA14),IF('Model inputs'!AA27="","",'Model inputs'!AA27))>'Model inputs'!AA24,IF(OR(IF(EXACT("30-van fleets","80-van fleets"),IF('Model inputs'!AA14="","",'Model inputs'!AA14),IF('Model inputs'!AA27="","",'Model inputs'!AA27))="",'Model inputs'!AA24=""),"",IF(EXACT("30-van fleets","80-van fleets"),IF('Model inputs'!AA14="","",'Model inputs'!AA14),IF('Model inputs'!AA27="","",'Model inputs'!AA27))>'Model inputs'!AA24))="",FALSE,IF(ISERROR(IF(EXACT("30-van fleets","80-van fleets"),IF('Model inputs'!AA14="","",'Model inputs'!AA14),IF('Model inputs'!AA27="","",'Model inputs'!AA27))>'Model inputs'!AA24),IF(EXACT("30-van fleets","80-van fleets"),IF('Model inputs'!AA14="","",'Model inputs'!AA14),IF('Model inputs'!AA27="","",'Model inputs'!AA27))>'Model inputs'!AA24,IF(OR(IF(EXACT("30-van fleets","80-van fleets"),IF('Model inputs'!AA14="","",'Model inputs'!AA14),IF('Model inputs'!AA27="","",'Model inputs'!AA27))="",'Model inputs'!AA24=""),"",IF(EXACT("30-van fleets","80-van fleets"),IF('Model inputs'!AA14="","",'Model inputs'!AA14),IF('Model inputs'!AA27="","",'Model inputs'!AA27))>'Model inputs'!AA24))),IF('Model inputs'!AA11="","",'Model inputs'!AA11),0)) -> 0 | C20: ='Fleet growth and revenue'!C9*IF(IF(IF(IF(ISERROR(IF(EXACT("30-van fleets","80-van fleets"),IF('Model inputs'!AA14="","",'Model inputs'!AA14),IF('Model inputs'!AA27="","",'Model inputs'!AA27))>'Model inputs'!AA24),IF(EXACT("30-van fleets","80-van fleets"),IF('Model inputs'!AA14="","",'Model inputs'!AA14),IF('Model inputs'!AA27="","",'Model inputs'!AA27))>'Model inputs'!AA24,IF(OR(IF(EXACT("30-van fleets","80-van fleets"),IF('Model inputs'!AA14="","",'Model inputs'!AA14),IF('Model inputs'!AA27="","",'Model inputs'!AA27))="",'Model inputs'!AA24=""),"",IF(EXACT("30-van fleets","80-van fleets"),IF('Model inputs'!AA14="","",'Model inputs'!AA14),IF('Model inputs'!AA27="","",'Model inputs'!AA27))>'Model inputs'!AA24))="",FALSE,IF(ISERROR(IF(EXACT("30-van fleets","80-van fleets"),IF('Model inputs'!AA14="","",'Model inputs'!AA14),IF('Model inputs'!AA27="","",'Model inputs'!AA27))>'Model inputs'!AA24),IF(EXACT("30-van fleets","80-van fleets"),IF('Model inputs'!AA14="","",'Model inputs'!AA14),IF('Model inputs'!AA27="","",'Model inputs'!AA27))>'Model inputs'!AA24,IF(OR(IF(EXACT("30-van fleets","80-van fleets"),IF('Model inputs'!AA14="","",'Model inputs'!AA14),IF('Model inputs'!AA27="","",'Model inputs'!AA27))="",'Model inputs'!AA24=""),"",IF(EXACT("30-van fleets","80-van fleets"),IF('Model inputs'!AA14="","",'Model inputs'!AA14),IF('Model inputs'!AA27="","",'Model inputs'!AA27))>'Model inputs'!AA24))),IF('Model inputs'!AA11="","",'Model inputs'!AA11),0)="",0,IF(IF(IF(ISERROR(IF(EXACT("30-van fleets","80-van fleets"),IF('Model inputs'!AA14="","",'Model inputs'!AA14),IF('Model inputs'!AA27="","",'Model inputs'!AA27))>'Model inputs'!AA24),IF(EXACT("30-van fleets","80-van fleets"),IF('Model inputs'!AA14="","",'Model inputs'!AA14),IF('Model inputs'!AA27="","",'Model inputs'!AA27))>'Model inputs'!AA24,IF(OR(IF(EXACT("30-van fleets","80-van fleets"),IF('Model inputs'!AA14="","",'Model inputs'!AA14),IF('Model inputs'!AA27="","",'Model inputs'!AA27))="",'Model inputs'!AA24=""),"",IF(EXACT("30-van fleets","80-van fleets"),IF('Model inputs'!AA14="","",'Model inputs'!AA14),IF('Model inputs'!AA27="","",'Model inputs'!AA27))>'Model inputs'!AA24))="",FALSE,IF(ISERROR(IF(EXACT("30-van fleets","80-van fleets"),IF('Model inputs'!AA14="","",'Model inputs'!AA14),IF('Model inputs'!AA27="","",'Model inputs'!AA27))>'Model inputs'!AA24),IF(EXACT("30-van fleets","80-van fleets"),IF('Model inputs'!AA14="","",'Model inputs'!AA14),IF('Model inputs'!AA27="","",'Model inputs'!AA27))>'Model inputs'!AA24,IF(OR(IF(EXACT("30-van fleets","80-van fleets"),IF('Model inputs'!AA14="","",'Model inputs'!AA14),IF('Model inputs'!AA27="","",'Model inputs'!AA27))="",'Model inputs'!AA24=""),"",IF(EXACT("30-van fleets","80-van fleets"),IF('Model inputs'!AA14="","",'Model inputs'!AA14),IF('Model inputs'!AA27="","",'Model inputs'!AA27))>'Model inputs'!AA24))),IF('Model inputs'!AA11="","",'Model inputs'!AA11),0)) -> 0 | D20: ='Fleet growth and revenue'!D9*IF(IF(IF(IF(ISERROR(IF(EXACT("30-van fleets","80-van fleets"),IF('Model inputs'!AA14="","",'Model inputs'!AA14),IF('Model inputs'!AA27="","",'Model inputs'!AA27))>'Model inputs'!AA24),IF(EXACT("30-van fleets","80-van fleets"),IF('Model inputs'!AA14="","",'Model inputs'!AA14),IF('Model inputs'!AA27="","",'Model inputs'!AA27))>'Model inputs'!AA24,IF(OR(IF(EXACT("30-van fleets","80-van fleets"),IF('Model inputs'!AA14="","",'Model inputs'!AA14),IF('Model inputs'!AA27="","",'Model inputs'!AA27))="",'Model inputs'!AA24=""),"",IF(EXACT("30-van fleets","80-van fleets"),IF('Model inputs'!AA14="","",'Model inputs'!AA14),IF('Model inputs'!AA27="","",'Model inputs'!AA27))>'Model inputs'!AA24))="",FALSE,IF(ISERROR(IF(EXACT("30-van fleets","80-van fleets"),IF('Model inputs'!AA14="","",'Model inputs'!AA14),IF('Model inputs'!AA27="","",'Model inputs'!AA27))>'Model inputs'!AA24),IF(EXACT("30-van fleets","80-van fleets"),IF('Model inputs'!AA14="","",'Model inputs'!AA14),IF('Model inputs'!AA27="","",'Model inputs'!AA27))>'Model inputs'!AA24,IF(OR(IF(EXACT("30-van fleets","80-van fleets"),IF('Model inputs'!AA14="","",'Model inputs'!AA14),IF('Model inputs'!AA27="","",'Model inputs'!AA27))="",'Model inputs'!AA24=""),"",IF(EXACT("30-van fleets","80-van fleets"),IF('Model inputs'!AA14="","",'Model inputs'!AA14),IF('Model inputs'!AA27="","",'Model inputs'!AA27))>'Model inputs'!AA24))),IF('Model inputs'!AA11="","",'Model inputs'!AA11),0)="",0,IF(IF(IF(ISERROR(IF(EXACT("30-van fleets","80-van fleets"),IF('Model inputs'!AA14="","",'Model inputs'!AA14),IF('Model inputs'!AA27="","",'Model inputs'!AA27))>'Model inputs'!AA24),IF(EXACT("30-van fleets","80-van fleets"),IF('Model inputs'!AA14="","",'Model inputs'!AA14),IF('Model inputs'!AA27="","",'Model inputs'!AA27))>'Model inputs'!AA24,IF(OR(IF(EXACT("30-van fleets","80-van fleets"),IF('Model inputs'!AA14="","",'Model inputs'!AA14),IF('Model inputs'!AA27="","",'Model inputs'!AA27))="",'Model inputs'!AA24=""),"",IF(EXACT("30-van fleets","80-van fleets"),IF('Model inputs'!AA14="","",'Model inputs'!AA14),IF('Model inputs'!AA27="","",'Model inputs'!AA27))>'Model inputs'!AA24))="",FALSE,IF(ISERROR(IF(EXACT("30-van fleets","80-van fleets"),IF('Model inputs'!AA14="","",'Model inputs'!AA14),IF('Model inputs'!AA27="","",'Model inputs'!AA27))>'Model inputs'!AA24),IF(EXACT("30-van fleets","80-van fleets"),IF('Model inputs'!AA14="","",'Model inputs'!AA14),IF('Model inputs'!AA27="","",'Model inputs'!AA27))>'Model inputs'!AA24,IF(OR(IF(EXACT("30-van fleets","80-van fleets"),IF('Model inputs'!AA14="","",'Model inputs'!AA14),IF('Model inputs'!AA27="","",'Model inputs'!AA27))="",'Model inputs'!AA24=""),"",IF(EXACT("30-van fleets","80-van fleets"),IF('Model inputs'!AA14="","",'Model inputs'!AA14),IF('Model inputs'!AA27="","",'Model inputs'!AA27))>'Model inputs'!AA24))),IF('Model inputs'!AA11="","",'Model inputs'!AA11),0)) -> 0 | E20: ='Fleet growth and revenue'!E9*IF(IF(IF(IF(ISERROR(IF(EXACT("30-van fleets","80-van fleets"),IF('Model inputs'!AA14="","",'Model inputs'!AA14),IF('Model inputs'!AA27="","",'Model inputs'!AA27))>'Model inputs'!AA24),IF(EXACT("30-van fleets","80-van fleets"),IF('Model inputs'!AA14="","",'Model inputs'!AA14),IF('Model inputs'!AA27="","",'Model inputs'!AA27))>'Model inputs'!AA24,IF(OR(IF(EXACT("30-van fleets","80-van fleets"),IF('Model inputs'!AA14="","",'Model inputs'!AA14),IF('Model inputs'!AA27="","",'Model inputs'!AA27))="",'Model inputs'!AA24=""),"",IF(EXACT("30-van fleets","80-van fleets"),IF('Model inputs'!AA14="","",'Model inputs'!AA14),IF('Model inputs'!AA27="","",'Model inputs'!AA27))>'Model inputs'!AA24))="",FALSE,IF(ISERROR(IF(EXACT("30-van fleets","80-van fleets"),IF('Model inputs'!AA14="","",'Model inputs'!AA14),IF('Model inputs'!AA27="","",'Model inputs'!AA27))>'Model inputs'!AA24),IF(EXACT("30-van fleets","80-van fleets"),IF('Model inputs'!AA14="","",'Model inputs'!AA14),IF('Model inputs'!AA27="","",'Model inputs'!AA27))>'Model inputs'!AA24,IF(OR(IF(EXACT("30-van fleets","80-van fleets"),IF('Model inputs'!AA14="","",'Model inputs'!AA14),IF('Model inputs'!AA27="","",'Model inputs'!AA27))="",'Model inputs'!AA24=""),"",IF(EXACT("30-van fleets","80-van fleets"),IF('Model inputs'!AA14="","",'Model inputs'!AA14),IF('Model inputs'!AA27="","",'Model inputs'!AA27))>'Model inputs'!AA24))),IF('Model inputs'!AA11="","",'Model inputs'!AA11),0)="",0,IF(IF(IF(ISERROR(IF(EXACT("30-van fleets","80-van fleets"),IF('Model inputs'!AA14="","",'Model inputs'!AA14),IF('Model inputs'!AA27="","",'Model inputs'!AA27))>'Model inputs'!AA24),IF(EXACT("30-van fleets","80-van fleets"),IF('Model inputs'!AA14="","",'Model inputs'!AA14),IF('Model inputs'!AA27="","",'Model inputs'!AA27))>'Model inputs'!AA24,IF(OR(IF(EXACT("30-van fleets","80-van fleets"),IF('Model inputs'!AA14="","",'Model inputs'!AA14),IF('Model inputs'!AA27="","",'Model inputs'!AA27))="",'Model inputs'!AA24=""),"",IF(EXACT("30-van fleets","80-van fleets"),IF('Model inputs'!AA14="","",'Model inputs'!AA14),IF('Model inputs'!AA27="","",'Model inputs'!AA27))>'Model inputs'!AA24))="",FALSE,IF(ISERROR(IF(EXACT("30-van fleets","80-van fleets"),IF('Model inputs'!AA14="","",'Model inputs'!AA14),IF('Model inputs'!AA27="","",'Model inputs'!AA27))>'Model inputs'!AA24),IF(EXACT("30-van fleets","80-van fleets"),IF('Model inputs'!AA14="","",'Model inputs'!AA14),IF('Model inputs'!AA27="","",'Model inputs'!AA27))>'Model inputs'!AA24,IF(OR(IF(EXACT("30-van fleets","80-van fleets"),IF('Model inputs'!AA14="","",'Model inputs'!AA14),IF('Model inputs'!AA27="","",'Model inputs'!AA27))="",'Model inputs'!AA24=""),"",IF(EXACT("30-van fleets","80-van fleets"),IF('Model inputs'!AA14="","",'Model inputs'!AA14),IF('Model inputs'!AA27="","",'Model inputs'!AA27))>'Model inputs'!AA24))),IF('Model inputs'!AA11="","",'Model inputs'!AA11),0)) -> 0 | F20: ='Fleet growth and revenue'!F9*IF(IF(IF(IF(ISERROR(IF(EXACT("30-van fleets","80-van fleets"),IF('Model inputs'!AA14="","",'Model inputs'!AA14),IF('Model inputs'!AA27="","",'Model inputs'!AA27))>'Model inputs'!AA24),IF(EXACT("30-van fleets","80-van fleets"),IF('Model inputs'!AA14="","",'Model inputs'!AA14),IF('Model inputs'!AA27="","",'Model inputs'!AA27))>'Model inputs'!AA24,IF(OR(IF(EXACT("30-van fleets","80-van fleets"),IF('Model inputs'!AA14="","",'Model inputs'!AA14),IF('Model inputs'!AA27="","",'Model inputs'!AA27))="",'Model inputs'!AA24=""),"",IF(EXACT("30-van fleets","80-van fleets"),IF('Model inputs'!AA14="","",'Model inputs'!AA14),IF('Model inputs'!AA27="","",'Model inputs'!AA27))>'Model inputs'!AA24))="",FALSE,IF(ISERROR(IF(EXACT("30-van fleets","80-van fleets"),IF('Model inputs'!AA14="","",'Model inputs'!AA14),IF('Model inputs'!AA27="","",'Model inputs'!AA27))>'Model inputs'!AA24),IF(EXACT("30-van fleets","80-van fleets"),IF('Model inputs'!AA14="","",'Model inputs'!AA14),IF('Model inputs'!AA27="","",'Model inputs'!AA27))>'Model inputs'!AA24,IF(OR(IF(EXACT("30-van fleets","80-van fleets"),IF('Model inputs'!AA14="","",'Model inputs'!AA14),IF('Model inputs'!AA27="","",'Model inputs'!AA27))="",'Model inputs'!AA24=""),"",IF(EXACT("30-van fleets","80-van fleets"),IF('Model inputs'!AA14="","",'Model inputs'!AA14),IF('Model inputs'!AA27="","",'Model inputs'!AA27))>'Model inputs'!AA24))),IF('Model inputs'!AA11="","",'Model inputs'!AA11),0)="",0,IF(IF(IF(ISERROR(IF(EXACT("30-van fleets","80-van fleets"),IF('Model inputs'!AA14="","",'Model inputs'!AA14),IF('Model inputs'!AA27="","",'Model inputs'!AA27))>'Model inputs'!AA24),IF(EXACT("30-van fleets","80-van fleets"),IF('Model inputs'!AA14="","",'Model inputs'!AA14),IF('Model inputs'!AA27="","",'Model inputs'!AA27))>'Model inputs'!AA24,IF(OR(IF(EXACT("30-van fleets","80-van fleets"),IF('Model inputs'!AA14="","",'Model inputs'!AA14),IF('Model inputs'!AA27="","",'Model inputs'!AA27))="",'Model inputs'!AA24=""),"",IF(EXACT("30-van fleets","80-van fleets"),IF('Model inputs'!AA14="","",'Model inputs'!AA14),IF('Model inputs'!AA27="","",'Model inputs'!AA27))>'Model inputs'!AA24))="",FALSE,IF(ISERROR(IF(EXACT("30-van fleets","80-van fleets"),IF('Model inputs'!AA14="","",'Model inputs'!AA14),IF('Model inputs'!AA27="","",'Model inputs'!AA27))>'Model inputs'!AA24),IF(EXACT("30-van fleets","80-van fleets"),IF('Model inputs'!AA14="","",'Model inputs'!AA14),IF('Model inputs'!AA27="","",'Model inputs'!AA27))>'Model inputs'!AA24,IF(OR(IF(EXACT("30-van fleets","80-van fleets"),IF('Model inputs'!AA14="","",'Model inputs'!AA14),IF('Model inputs'!AA27="","",'Model inputs'!AA27))="",'Model inputs'!AA24=""),"",IF(EXACT("30-van fleets","80-van fleets"),IF('Model inputs'!AA14="","",'Model inputs'!AA14),IF('Model inputs'!AA27="","",'Model inputs'!AA27))>'Model inputs'!AA24))),IF('Model inputs'!AA11="","",'Model inputs'!AA11),0)) -> 0 | G20: ='Fleet growth and revenue'!G9*IF(IF(IF(IF(ISERROR(IF(EXACT("30-van fleets","80-van fleets"),IF('Model inputs'!AA14="","",'Model inputs'!AA14),IF('Model inputs'!AA27="","",'Model inputs'!AA27))>'Model inputs'!AA24),IF(EXACT("30-van fleets","80-van fleets"),IF('Model inputs'!AA14="","",'Model inputs'!AA14),IF('Model inputs'!AA27="","",'Model inputs'!AA27))>'Model inputs'!AA24,IF(OR(IF(EXACT("30-van fleets","80-van fleets"),IF('Model inputs'!AA14="","",'Model inputs'!AA14),IF('Model inputs'!AA27="","",'Model inputs'!AA27))="",'Model inputs'!AA24=""),"",IF(EXACT("30-van fleets","80-van fleets"),IF('Model inputs'!AA14="","",'Model inputs'!AA14),IF('Model inputs'!AA27="","",'Model inputs'!AA27))>'Model inputs'!AA24))="",FALSE,IF(ISERROR(IF(EXACT("30-van fleets","80-van fleets"),IF('Model inputs'!AA14="","",'Model inputs'!AA14),IF('Model inputs'!AA27="","",'Model inputs'!AA27))>'Model inputs'!AA24),IF(EXACT("30-van fleets","80-van fleets"),IF('Model inputs'!AA14="","",'Model inputs'!AA14),IF('Model inputs'!AA27="","",'Model inputs'!AA27))>'Model inputs'!AA24,IF(OR(IF(EXACT("30-van fleets","80-van fleets"),IF('Model inputs'!AA14="","",'Model inputs'!AA14),IF('Model inputs'!AA27="","",'Model inputs'!AA27))="",'Model inputs'!AA24=""),"",IF(EXACT("30-van fleets","80-van fleets"),IF('Model inputs'!AA14="","",'Model inputs'!AA14),IF('Model inputs'!AA27="","",'Model inputs'!AA27))>'Model inputs'!AA24))),IF('Model inputs'!AA11="","",'Model inputs'!AA11),0)="",0,IF(IF(IF(ISERROR(IF(EXACT("30-van fleets","80-van fleets"),IF('Model inputs'!AA14="","",'Model inputs'!AA14),IF('Model inputs'!AA27="","",'Model inputs'!AA27))>'Model inputs'!AA24),IF(EXACT("30-van fleets","80-van fleets"),IF('Model inputs'!AA14="","",'Model inputs'!AA14),IF('Model inputs'!AA27="","",'Model inputs'!AA27))>'Model inputs'!AA24,IF(OR(IF(EXACT("30-van fleets","80-van fleets"),IF('Model inputs'!AA14="","",'Model inputs'!AA14),IF('Model inputs'!AA27="","",'Model inputs'!AA27))="",'Model inputs'!AA24=""),"",IF(EXACT("30-van fleets","80-van fleets"),IF('Model inputs'!AA14="","",'Model inputs'!AA14),IF('Model inputs'!AA27="","",'Model inputs'!AA27))>'Model inputs'!AA24))="",FALSE,IF(ISERROR(IF(EXACT("30-van fleets","80-van fleets"),IF('Model inputs'!AA14="","",'Model inputs'!AA14),IF('Model inputs'!AA27="","",'Model inputs'!AA27))>'Model inputs'!AA24),IF(EXACT("30-van fleets","80-van fleets"),IF('Model inputs'!AA14="","",'Model inputs'!AA14),IF('Model inputs'!AA27="","",'Model inputs'!AA27))>'Model inputs'!AA24,IF(OR(IF(EXACT("30-van fleets","80-van fleets"),IF('Model inputs'!AA14="","",'Model inputs'!AA14),IF('Model inputs'!AA27="","",'Model inputs'!AA27))="",'Model inputs'!AA24=""),"",IF(EXACT("30-van fleets","80-van fleets"),IF('Model inputs'!AA14="","",'Model inputs'!AA14),IF('Model inputs'!AA27="","",'Model inputs'!AA27))>'Model inputs'!AA24))),IF('Model inputs'!AA11="","",'Model inputs'!AA11),0)) -> 0 | H20: ='Fleet growth and revenue'!H9*IF(IF(IF(IF(ISERROR(IF(EXACT("30-van fleets","80-van fleets"),IF('Model inputs'!AA14="","",'Model inputs'!AA14),IF('Model inputs'!AA27="","",'Model inputs'!AA27))>'Model inputs'!AA24),IF(EXACT("30-van fleets","80-van fleets"),IF('Model inputs'!AA14="","",'Model inputs'!AA14),IF('Model inputs'!AA27="","",'Model inputs'!AA27))>'Model inputs'!AA24,IF(OR(IF(EXACT("30-van fleets","80-van fleets"),IF('Model inputs'!AA14="","",'Model inputs'!AA14),IF('Model inputs'!AA27="","",'Model inputs'!AA27))="",'Model inputs'!AA24=""),"",IF(EXACT("30-van fleets","80-van fleets"),IF('Model inputs'!AA14="","",'Model inputs'!AA14),IF('Model inputs'!AA27="","",'Model inputs'!AA27))>'Model inputs'!AA24))="",FALSE,IF(ISERROR(IF(EXACT("30-van fleets","80-van fleets"),IF('Model inputs'!AA14="","",'Model inputs'!AA14),IF('Model inputs'!AA27="","",'Model inputs'!AA27))>'Model inputs'!AA24),IF(EXACT("30-van fleets","80-van fleets"),IF('Model inputs'!AA14="","",'Model inputs'!AA14),IF('Model inputs'!AA27="","",'Model inputs'!AA27))>'Model inputs'!AA24,IF(OR(IF(EXACT("30-van fleets","80-van fleets"),IF('Model inputs'!AA14="","",'Model inputs'!AA14),IF('Model inputs'!AA27="","",'Model inputs'!AA27))="",'Model inputs'!AA24=""),"",IF(EXACT("30-van fleets","80-van fleets"),IF('Model inputs'!AA14="","",'Model inputs'!AA14),IF('Model inputs'!AA27="","",'Model inputs'!AA27))>'Model inputs'!AA24))),IF('Model inputs'!AA11="","",'Model inputs'!AA11),0)="",0,IF(IF(IF(ISERROR(IF(EXACT("30-van fleets","80-van fleets"),IF('Model inputs'!AA14="","",'Model inputs'!AA14),IF('Model inputs'!AA27="","",'Model inputs'!AA27))>'Model inputs'!AA24),IF(EXACT("30-van fleets","80-van fleets"),IF('Model inputs'!AA14="","",'Model inputs'!AA14),IF('Model inputs'!AA27="","",'Model inputs'!AA27))>'Model inputs'!AA24,IF(OR(IF(EXACT("30-van fleets","80-van fleets"),IF('Model inputs'!AA14="","",'Model inputs'!AA14),IF('Model inputs'!AA27="","",'Model inputs'!AA27))="",'Model inputs'!AA24=""),"",IF(EXACT("30-van fleets","80-van fleets"),IF('Model inputs'!AA14="","",'Model inputs'!AA14),IF('Model inputs'!AA27="","",'Model inputs'!AA27))>'Model inputs'!AA24))="",FALSE,IF(ISERROR(IF(EXACT("30-van fleets","80-van fleets"),IF('Model inputs'!AA14="","",'Model inputs'!AA14),IF('Model inputs'!AA27="","",'Model inputs'!AA27))>'Model inputs'!AA24),IF(EXACT("30-van fleets","80-van fleets"),IF('Model inputs'!AA14="","",'Model inputs'!AA14),IF('Model inputs'!AA27="","",'Model inputs'!AA27))>'Model inputs'!AA24,IF(OR(IF(EXACT("30-van fleets","80-van fleets"),IF('Model inputs'!AA14="","",'Model inputs'!AA14),IF('Model inputs'!AA27="","",'Model inputs'!AA27))="",'Model inputs'!AA24=""),"",IF(EXACT("30-van fleets","80-van fleets"),IF('Model inputs'!AA14="","",'Model inputs'!AA14),IF('Model inputs'!AA27="","",'Model inputs'!AA27))>'Model inputs'!AA24))),IF('Model inputs'!AA11="","",'Model inputs'!AA11),0)) -> 0 | I20: ='Fleet growth and revenue'!I9*IF(IF(IF(IF(ISERROR(IF(EXACT("30-van fleets","80-van fleets"),IF('Model inputs'!AA14="","",'Model inputs'!AA14),IF('Model inputs'!AA27="","",'Model inputs'!AA27))>'Model inputs'!AA24),IF(EXACT("30-van fleets","80-van fleets"),IF('Model inputs'!AA14="","",'Model inputs'!AA14),IF('Model inputs'!AA27="","",'Model inputs'!AA27))>'Model inputs'!AA24,IF(OR(IF(EXACT("30-van fleets","80-van fleets"),IF('Model inputs'!AA14="","",'Model inputs'!AA14),IF('Model inputs'!AA27="","",'Model inputs'!AA27))="",'Model inputs'!AA24=""),"",IF(EXACT("30-van fleets","80-van fleets"),IF('Model inputs'!AA14="","",'Model inputs'!AA14),IF('Model inputs'!AA27="","",'Model inputs'!AA27))>'Model inputs'!AA24))="",FALSE,IF(ISERROR(IF(EXACT("30-van fleets","80-van fleets"),IF('Model inputs'!AA14="","",'Model inputs'!AA14),IF('Model inputs'!AA27="","",'Model inputs'!AA27))>'Model inputs'!AA24),IF(EXACT("30-van fleets","80-van fleets"),IF('Model inputs'!AA14="","",'Model inputs'!AA14),IF('Model inputs'!AA27="","",'Model inputs'!AA27))>'Model inputs'!AA24,IF(OR(IF(EXACT("30-van fleets","80-van fleets"),IF('Model inputs'!AA14="","",'Model inputs'!AA14),IF('Model inputs'!AA27="","",'Model inputs'!AA27))="",'Model inputs'!AA24=""),"",IF(EXACT("30-van fleets","80-van fleets"),IF('Model inputs'!AA14="","",'Model inputs'!AA14),IF('Model inputs'!AA27="","",'Model inputs'!AA27))>'Model inputs'!AA24))),IF('Model inputs'!AA11="","",'Model inputs'!AA11),0)="",0,IF(IF(IF(ISERROR(IF(EXACT("30-van fleets","80-van fleets"),IF('Model inputs'!AA14="","",'Model inputs'!AA14),IF('Model inputs'!AA27="","",'Model inputs'!AA27))>'Model inputs'!AA24),IF(EXACT("30-van fleets","80-van fleets"),IF('Model inputs'!AA14="","",'Model inputs'!AA14),IF('Model inputs'!AA27="","",'Model inputs'!AA27))>'Model inputs'!AA24,IF(OR(IF(EXACT("30-van fleets","80-van fleets"),IF('Model inputs'!AA14="","",'Model inputs'!AA14),IF('Model inputs'!AA27="","",'Model inputs'!AA27))="",'Model inputs'!AA24=""),"",IF(EXACT("30-van fleets","80-van fleets"),IF('Model inputs'!AA14="","",'Model inputs'!AA14),IF('Model inputs'!AA27="","",'Model inputs'!AA27))>'Model inputs'!AA24))="",FALSE,IF(ISERROR(IF(EXACT("30-van fleets","80-van fleets"),IF('Model inputs'!AA14="","",'Model inputs'!AA14),IF('Model inputs'!AA27="","",'Model inputs'!AA27))>'Model inputs'!AA24),IF(EXACT("30-van fleets","80-van fleets"),IF('Model inputs'!AA14="","",'Model inputs'!AA14),IF('Model inputs'!AA27="","",'Model inputs'!AA27))>'Model inputs'!AA24,IF(OR(IF(EXACT("30-van fleets","80-van fleets"),IF('Model inputs'!AA14="","",'Model inputs'!AA14),IF('Model inputs'!AA27="","",'Model inputs'!AA27))="",'Model inputs'!AA24=""),"",IF(EXACT("30-van fleets","80-van fleets"),IF('Model inputs'!AA14="","",'Model inputs'!AA14),IF('Model inputs'!AA27="","",'Model inputs'!AA27))>'Model inputs'!AA24))),IF('Model inputs'!AA11="","",'Model inputs'!AA11),0)) -> 0 | J20: ='Fleet growth and revenue'!J9*IF(IF(IF(IF(ISERROR(IF(EXACT("30-van fleets","80-van fleets"),IF('Model inputs'!AA14="","",'Model inputs'!AA14),IF('Model inputs'!AA27="","",'Model inputs'!AA27))>'Model inputs'!AA24),IF(EXACT("30-van fleets","80-van fleets"),IF('Model inputs'!AA14="","",'Model inputs'!AA14),IF('Model inputs'!AA27="","",'Model inputs'!AA27))>'Model inputs'!AA24,IF(OR(IF(EXACT("30-van fleets","80-van fleets"),IF('Model inputs'!AA14="","",'Model inputs'!AA14),IF('Model inputs'!AA27="","",'Model inputs'!AA27))="",'Model inputs'!AA24=""),"",IF(EXACT("30-van fleets","80-van fleets"),IF('Model inputs'!AA14="","",'Model inputs'!AA14),IF('Model inputs'!AA27="","",'Model inputs'!AA27))>'Model inputs'!AA24))="",FALSE,IF(ISERROR(IF(EXACT("30-van fleets","80-van fleets"),IF('Model inputs'!AA14="","",'Model inputs'!AA14),IF('Model inputs'!AA27="","",'Model inputs'!AA27))>'Model inputs'!AA24),IF(EXACT("30-van fleets","80-van fleets"),IF('Model inputs'!AA14="","",'Model inputs'!AA14),IF('Model inputs'!AA27="","",'Model inputs'!AA27))>'Model inputs'!AA24,IF(OR(IF(EXACT("30-van fleets","80-van fleets"),IF('Model inputs'!AA14="","",'Model inputs'!AA14),IF('Model inputs'!AA27="","",'Model inputs'!AA27))="",'Model inputs'!AA24=""),"",IF(EXACT("30-van fleets","80-van fleets"),IF('Model inputs'!AA14="","",'Model inputs'!AA14),IF('Model inputs'!AA27="","",'Model inputs'!AA27))>'Model inputs'!AA24))),IF('Model inputs'!AA11="","",'Model inputs'!AA11),0)="",0,IF(IF(IF(ISERROR(IF(EXACT("30-van fleets","80-van fleets"),IF('Model inputs'!AA14="","",'Model inputs'!AA14),IF('Model inputs'!AA27="","",'Model inputs'!AA27))>'Model inputs'!AA24),IF(EXACT("30-van fleets","80-van fleets"),IF('Model inputs'!AA14="","",'Model inputs'!AA14),IF('Model inputs'!AA27="","",'Model inputs'!AA27))>'Model inputs'!AA24,IF(OR(IF(EXACT("30-van fleets","80-van fleets"),IF('Model inputs'!AA14="","",'Model inputs'!AA14),IF('Model inputs'!AA27="","",'Model inputs'!AA27))="",'Model inputs'!AA24=""),"",IF(EXACT("30-van fleets","80-van fleets"),IF('Model inputs'!AA14="","",'Model inputs'!AA14),IF('Model inputs'!AA27="","",'Model inputs'!AA27))>'Model inputs'!AA24))="",FALSE,IF(ISERROR(IF(EXACT("30-van fleets","80-van fleets"),IF('Model inputs'!AA14="","",'Model inputs'!AA14),IF('Model inputs'!AA27="","",'Model inputs'!AA27))>'Model inputs'!AA24),IF(EXACT("30-van fleets","80-van fleets"),IF('Model inputs'!AA14="","",'Model inputs'!AA14),IF('Model inputs'!AA27="","",'Model inputs'!AA27))>'Model inputs'!AA24,IF(OR(IF(EXACT("30-van fleets","80-van fleets"),IF('Model inputs'!AA14="","",'Model inputs'!AA14),IF('Model inputs'!AA27="","",'Model inputs'!AA27))="",'Model inputs'!AA24=""),"",IF(EXACT("30-van fleets","80-van fleets"),IF('Model inputs'!AA14="","",'Model inputs'!AA14),IF('Model inputs'!AA27="","",'Model inputs'!AA27))>'Model inputs'!AA24))),IF('Model inputs'!AA11="","",'Model inputs'!AA11),0)) -> 0 | K20: ='Fleet growth and revenue'!K9*IF(IF(IF(IF(ISERROR(IF(EXACT("30-van fleets","80-van fleets"),IF('Model inputs'!AA14="","",'Model inputs'!AA14),IF('Model inputs'!AA27="","",'Model inputs'!AA27))>'Model inputs'!AA24),IF(EXACT("30-van fleets","80-van fleets"),IF('Model inputs'!AA14="","",'Model inputs'!AA14),IF('Model inputs'!AA27="","",'Model inputs'!AA27))>'Model inputs'!AA24,IF(OR(IF(EXACT("30-van fleets","80-van fleets"),IF('Model inputs'!AA14="","",'Model inputs'!AA14),IF('Model inputs'!AA27="","",'Model inputs'!AA27))="",'Model inputs'!AA24=""),"",IF(EXACT("30-van fleets","80-van fleets"),IF('Model inputs'!AA14="","",'Model inputs'!AA14),IF('Model inputs'!AA27="","",'Model inputs'!AA27))>'Model inputs'!AA24))="",FALSE,IF(ISERROR(IF(EXACT("30-van fleets","80-van fleets"),IF('Model inputs'!AA14="","",'Model inputs'!AA14),IF('Model inputs'!AA27="","",'Model inputs'!AA27))>'Model inputs'!AA24),IF(EXACT("30-van fleets","80-van fleets"),IF('Model inputs'!AA14="","",'Model inputs'!AA14),IF('Model inputs'!AA27="","",'Model inputs'!AA27))>'Model inputs'!AA24,IF(OR(IF(EXACT("30-van fleets","80-van fleets"),IF('Model inputs'!AA14="","",'Model inputs'!AA14),IF('Model inputs'!AA27="","",'Model inputs'!AA27))="",'Model inputs'!AA24=""),"",IF(EXACT("30-van fleets","80-van fleets"),IF('Model inputs'!AA14="","",'Model inputs'!AA14),IF('Model inputs'!AA27="","",'Model inputs'!AA27))>'Model inputs'!AA24))),IF('Model inputs'!AA11="","",'Model inputs'!AA11),0)="",0,IF(IF(IF(ISERROR(IF(EXACT("30-van fleets","80-van fleets"),IF('Model inputs'!AA14="","",'Model inputs'!AA14),IF('Model inputs'!AA27="","",'Model inputs'!AA27))>'Model inputs'!AA24),IF(EXACT("30-van fleets","80-van fleets"),IF('Model inputs'!AA14="","",'Model inputs'!AA14),IF('Model inputs'!AA27="","",'Model inputs'!AA27))>'Model inputs'!AA24,IF(OR(IF(EXACT("30-van fleets","80-van fleets"),IF('Model inputs'!AA14="","",'Model inputs'!AA14),IF('Model inputs'!AA27="","",'Model inputs'!AA27))="",'Model inputs'!AA24=""),"",IF(EXACT("30-van fleets","80-van fleets"),IF('Model inputs'!AA14="","",'Model inputs'!AA14),IF('Model inputs'!AA27="","",'Model inputs'!AA27))>'Model inputs'!AA24))="",FALSE,IF(ISERROR(IF(EXACT("30-van fleets","80-van fleets"),IF('Model inputs'!AA14="","",'Model inputs'!AA14),IF('Model inputs'!AA27="","",'Model inputs'!AA27))>'Model inputs'!AA24),IF(EXACT("30-van fleets","80-van fleets"),IF('Model inputs'!AA14="","",'Model inputs'!AA14),IF('Model inputs'!AA27="","",'Model inputs'!AA27))>'Model inputs'!AA24,IF(OR(IF(EXACT("30-van fleets","80-van fleets"),IF('Model inputs'!AA14="","",'Model inputs'!AA14),IF('Model inputs'!AA27="","",'Model inputs'!AA27))="",'Model inputs'!AA24=""),"",IF(EXACT("30-van fleets","80-van fleets"),IF('Model inputs'!AA14="","",'Model inputs'!AA14),IF('Model inputs'!AA27="","",'Model inputs'!AA27))>'Model inputs'!AA24))),IF('Model inputs'!AA11="","",'Model inputs'!AA11),0)) -> 0 | L20: ='Fleet growth and revenue'!L9*IF(IF(IF(IF(ISERROR(IF(EXACT("30-van fleets","80-van fleets"),IF('Model inputs'!AA14="","",'Model inputs'!AA14),IF('Model inputs'!AA27="","",'Model inputs'!AA27))>'Model inputs'!AA24),IF(EXACT("30-van fleets","80-van fleets"),IF('Model inputs'!AA14="","",'Model inputs'!AA14),IF('Model inputs'!AA27="","",'Model inputs'!AA27))>'Model inputs'!AA24,IF(OR(IF(EXACT("30-van fleets","80-van fleets"),IF('Model inputs'!AA14="","",'Model inputs'!AA14),IF('Model inputs'!AA27="","",'Model inputs'!AA27))="",'Model inputs'!AA24=""),"",IF(EXACT("30-van fleets","80-van fleets"),IF('Model inputs'!AA14="","",'Model inputs'!AA14),IF('Model inputs'!AA27="","",'Model inputs'!AA27))>'Model inputs'!AA24))="",FALSE,IF(ISERROR(IF(EXACT("30-van fleets","80-van fleets"),IF('Model inputs'!AA14="","",'Model inputs'!AA14),IF('Model inputs'!AA27="","",'Model inputs'!AA27))>'Model inputs'!AA24),IF(EXACT("30-van fleets","80-van fleets"),IF('Model inputs'!AA14="","",'Model inputs'!AA14),IF('Model inputs'!AA27="","",'Model inputs'!AA27))>'Model inputs'!AA24,IF(OR(IF(EXACT("30-van fleets","80-van fleets"),IF('Model inputs'!AA14="","",'Model inputs'!AA14),IF('Model inputs'!AA27="","",'Model inputs'!AA27))="",'Model inputs'!AA24=""),"",IF(EXACT("30-van fleets","80-van fleets"),IF('Model inputs'!AA14="","",'Model inputs'!AA14),IF('Model inputs'!AA27="","",'Model inputs'!AA27))>'Model inputs'!AA24))),IF('Model inputs'!AA11="","",'Model inputs'!AA11),0)="",0,IF(IF(IF(ISERROR(IF(EXACT("30-van fleets","80-van fleets"),IF('Model inputs'!AA14="","",'Model inputs'!AA14),IF('Model inputs'!AA27="","",'Model inputs'!AA27))>'Model inputs'!AA24),IF(EXACT("30-van fleets","80-van fleets"),IF('Model inputs'!AA14="","",'Model inputs'!AA14),IF('Model inputs'!AA27="","",'Model inputs'!AA27))>'Model inputs'!AA24,IF(OR(IF(EXACT("30-van fleets","80-van fleets"),IF('Model inputs'!AA14="","",'Model inputs'!AA14),IF('Model inputs'!AA27="","",'Model inputs'!AA27))="",'Model inputs'!AA24=""),"",IF(EXACT("30-van fleets","80-van fleets"),IF('Model inputs'!AA14="","",'Model inputs'!AA14),IF('Model inputs'!AA27="","",'Model inputs'!AA27))>'Model inputs'!AA24))="",FALSE,IF(ISERROR(IF(EXACT("30-van fleets","80-van fleets"),IF('Model inputs'!AA14="","",'Model inputs'!AA14),IF('Model inputs'!AA27="","",'Model inputs'!AA27))>'Model inputs'!AA24),IF(EXACT("30-van fleets","80-van fleets"),IF('Model inputs'!AA14="","",'Model inputs'!AA14),IF('Model inputs'!AA27="","",'Model inputs'!AA27))>'Model inputs'!AA24,IF(OR(IF(EXACT("30-van fleets","80-van fleets"),IF('Model inputs'!AA14="","",'Model inputs'!AA14),IF('Model inputs'!AA27="","",'Model inputs'!AA27))="",'Model inputs'!AA24=""),"",IF(EXACT("30-van fleets","80-van fleets"),IF('Model inputs'!AA14="","",'Model inputs'!AA14),IF('Model inputs'!AA27="","",'Model inputs'!AA27))>'Model inputs'!AA24))),IF('Model inputs'!AA11="","",'Model inputs'!AA11),0)) -> 0 | M20: ='Fleet growth and revenue'!M9*IF(IF(IF(IF(ISERROR(IF(EXACT("30-van fleets","80-van fleets"),IF('Model inputs'!AA14="","",'Model inputs'!AA14),IF('Model inputs'!AA27="","",'Model inputs'!AA27))>'Model inputs'!AA24),IF(EXACT("30-van fleets","80-van fleets"),IF('Model inputs'!AA14="","",'Model inputs'!AA14),IF('Model inputs'!AA27="","",'Model inputs'!AA27))>'Model inputs'!AA24,IF(OR(IF(EXACT("30-van fleets","80-van fleets"),IF('Model inputs'!AA14="","",'Model inputs'!AA14),IF('Model inputs'!AA27="","",'Model inputs'!AA27))="",'Model inputs'!AA24=""),"",IF(EXACT("30-van fleets","80-van fleets"),IF('Model inputs'!AA14="","",'Model inputs'!AA14),IF('Model inputs'!AA27="","",'Model inputs'!AA27))>'Model inputs'!AA24))="",FALSE,IF(ISERROR(IF(EXACT("30-van fleets","80-van fleets"),IF('Model inputs'!AA14="","",'Model inputs'!AA14),IF('Model inputs'!AA27="","",'Model inputs'!AA27))>'Model inputs'!AA24),IF(EXACT("30-van fleets","80-van fleets"),IF('Model inputs'!AA14="","",'Model inputs'!AA14),IF('Model inputs'!AA27="","",'Model inputs'!AA27))>'Model inputs'!AA24,IF(OR(IF(EXACT("30-van fleets","80-van fleets"),IF('Model inputs'!AA14="","",'Model inputs'!AA14),IF('Model inputs'!AA27="","",'Model inputs'!AA27))="",'Model inputs'!AA24=""),"",IF(EXACT("30-van fleets","80-van fleets"),IF('Model inputs'!AA14="","",'Model inputs'!AA14),IF('Model inputs'!AA27="","",'Model inputs'!AA27))>'Model inputs'!AA24))),IF('Model inputs'!AA11="","",'Model inputs'!AA11),0)="",0,IF(IF(IF(ISERROR(IF(EXACT("30-van fleets","80-van fleets"),IF('Model inputs'!AA14="","",'Model inputs'!AA14),IF('Model inputs'!AA27="","",'Model inputs'!AA27))>'Model inputs'!AA24),IF(EXACT("30-van fleets","80-van fleets"),IF('Model inputs'!AA14="","",'Model inputs'!AA14),IF('Model inputs'!AA27="","",'Model inputs'!AA27))>'Model inputs'!AA24,IF(OR(IF(EXACT("30-van fleets","80-van fleets"),IF('Model inputs'!AA14="","",'Model inputs'!AA14),IF('Model inputs'!AA27="","",'Model inputs'!AA27))="",'Model inputs'!AA24=""),"",IF(EXACT("30-van fleets","80-van fleets"),IF('Model inputs'!AA14="","",'Model inputs'!AA14),IF('Model inputs'!AA27="","",'Model inputs'!AA27))>'Model inputs'!AA24))="",FALSE,IF(ISERROR(IF(EXACT("30-van fleets","80-van fleets"),IF('Model inputs'!AA14="","",'Model inputs'!AA14),IF('Model inputs'!AA27="","",'Model inputs'!AA27))>'Model inputs'!AA24),IF(EXACT("30-van fleets","80-van fleets"),IF('Model inputs'!AA14="","",'Model inputs'!AA14),IF('Model inputs'!AA27="","",'Model inputs'!AA27))>'Model inputs'!AA24,IF(OR(IF(EXACT("30-van fleets","80-van fleets"),IF('Model inputs'!AA14="","",'Model inputs'!AA14),IF('Model inputs'!AA27="","",'Model inputs'!AA27))="",'Model inputs'!AA24=""),"",IF(EXACT("30-van fleets","80-van fleets"),IF('Model inputs'!AA14="","",'Model inputs'!AA14),IF('Model inputs'!AA27="","",'Model inputs'!AA27))>'Model inputs'!AA24))),IF('Model inputs'!AA11="","",'Model inputs'!AA11),0)) -> 0 | N20: ='Fleet growth and revenue'!N9*IF(IF(IF(IF(ISERROR(IF(EXACT("30-van fleets","80-van fleets"),IF('Model inputs'!AA14="","",'Model inputs'!AA14),IF('Model inputs'!AA27="","",'Model inputs'!AA27))>'Model inputs'!AA24),IF(EXACT("30-van fleets","80-van fleets"),IF('Model inputs'!AA14="","",'Model inputs'!AA14),IF('Model inputs'!AA27="","",'Model inputs'!AA27))>'Model inputs'!AA24,IF(OR(IF(EXACT("30-van fleets","80-van fleets"),IF('Model inputs'!AA14="","",'Model inputs'!AA14),IF('Model inputs'!AA27="","",'Model inputs'!AA27))="",'Model inputs'!AA24=""),"",IF(EXACT("30-van fleets","80-van fleets"),IF('Model inputs'!AA14="","",'Model inputs'!AA14),IF('Model inputs'!AA27="","",'Model inputs'!AA27))>'Model inputs'!AA24))="",FALSE,IF(ISERROR(IF(EXACT("30-van fleets","80-van fleets"),IF('Model inputs'!AA14="","",'Model inputs'!AA14),IF('Model inputs'!AA27="","",'Model inputs'!AA27))>'Model inputs'!AA24),IF(EXACT("30-van fleets","80-van fleets"),IF('Model inputs'!AA14="","",'Model inputs'!AA14),IF('Model inputs'!AA27="","",'Model inputs'!AA27))>'Model inputs'!AA24,IF(OR(IF(EXACT("30-van fleets","80-van fleets"),IF('Model inputs'!AA14="","",'Model inputs'!AA14),IF('Model inputs'!AA27="","",'Model inputs'!AA27))="",'Model inputs'!AA24=""),"",IF(EXACT("30-van fleets","80-van fleets"),IF('Model inputs'!AA14="","",'Model inputs'!AA14),IF('Model inputs'!AA27="","",'Model inputs'!AA27))>'Model inputs'!AA24))),IF('Model inputs'!AA11="","",'Model inputs'!AA11),0)="",0,IF(IF(IF(ISERROR(IF(EXACT("30-van fleets","80-van fleets"),IF('Model inputs'!AA14="","",'Model inputs'!AA14),IF('Model inputs'!AA27="","",'Model inputs'!AA27))>'Model inputs'!AA24),IF(EXACT("30-van fleets","80-van fleets"),IF('Model inputs'!AA14="","",'Model inputs'!AA14),IF('Model inputs'!AA27="","",'Model inputs'!AA27))>'Model inputs'!AA24,IF(OR(IF(EXACT("30-van fleets","80-van fleets"),IF('Model inputs'!AA14="","",'Model inputs'!AA14),IF('Model inputs'!AA27="","",'Model inputs'!AA27))="",'Model inputs'!AA24=""),"",IF(EXACT("30-van fleets","80-van fleets"),IF('Model inputs'!AA14="","",'Model inputs'!AA14),IF('Model inputs'!AA27="","",'Model inputs'!AA27))>'Model inputs'!AA24))="",FALSE,IF(ISERROR(IF(EXACT("30-van fleets","80-van fleets"),IF('Model inputs'!AA14="","",'Model inputs'!AA14),IF('Model inputs'!AA27="","",'Model inputs'!AA27))>'Model inputs'!AA24),IF(EXACT("30-van fleets","80-van fleets"),IF('Model inputs'!AA14="","",'Model inputs'!AA14),IF('Model inputs'!AA27="","",'Model inputs'!AA27))>'Model inputs'!AA24,IF(OR(IF(EXACT("30-van fleets","80-van fleets"),IF('Model inputs'!AA14="","",'Model inputs'!AA14),IF('Model inputs'!AA27="","",'Model inputs'!AA27))="",'Model inputs'!AA24=""),"",IF(EXACT("30-van fleets","80-van fleets"),IF('Model inputs'!AA14="","",'Model inputs'!AA14),IF('Model inputs'!AA27="","",'Model inputs'!AA27))>'Model inputs'!AA24))),IF('Model inputs'!AA11="","",'Model inputs'!AA11),0)) -> 0 | O20: ='Fleet growth and revenue'!O9*IF(IF(IF(IF(ISERROR(IF(EXACT("30-van fleets","80-van fleets"),IF('Model inputs'!AA14="","",'Model inputs'!AA14),IF('Model inputs'!AA27="","",'Model inputs'!AA27))>'Model inputs'!AA24),IF(EXACT("30-van fleets","80-van fleets"),IF('Model inputs'!AA14="","",'Model inputs'!AA14),IF('Model inputs'!AA27="","",'Model inputs'!AA27))>'Model inputs'!AA24,IF(OR(IF(EXACT("30-van fleets","80-van fleets"),IF('Model inputs'!AA14="","",'Model inputs'!AA14),IF('Model inputs'!AA27="","",'Model inputs'!AA27))="",'Model inputs'!AA24=""),"",IF(EXACT("30-van fleets","80-van fleets"),IF('Model inputs'!AA14="","",'Model inputs'!AA14),IF('Model inputs'!AA27="","",'Model inputs'!AA27))>'Model inputs'!AA24))="",FALSE,IF(ISERROR(IF(EXACT("30-van fleets","80-van fleets"),IF('Model inputs'!AA14="","",'Model inputs'!AA14),IF('Model inputs'!AA27="","",'Model inputs'!AA27))>'Model inputs'!AA24),IF(EXACT("30-van fleets","80-van fleets"),IF('Model inputs'!AA14="","",'Model inputs'!AA14),IF('Model inputs'!AA27="","",'Model inputs'!AA27))>'Model inputs'!AA24,IF(OR(IF(EXACT("30-van fleets","80-van fleets"),IF('Model inputs'!AA14="","",'Model inputs'!AA14),IF('Model inputs'!AA27="","",'Model inputs'!AA27))="",'Model inputs'!AA24=""),"",IF(EXACT("30-van fleets","80-van fleets"),IF('Model inputs'!AA14="","",'Model inputs'!AA14),IF('Model inputs'!AA27="","",'Model inputs'!AA27))>'Model inputs'!AA24))),IF('Model inputs'!AA11="","",'Model inputs'!AA11),0)="",0,IF(IF(IF(ISERROR(IF(EXACT("30-van fleets","80-van fleets"),IF('Model inputs'!AA14="","",'Model inputs'!AA14),IF('Model inputs'!AA27="","",'Model inputs'!AA27))>'Model inputs'!AA24),IF(EXACT("30-van fleets","80-van fleets"),IF('Model inputs'!AA14="","",'Model inputs'!AA14),IF('Model inputs'!AA27="","",'Model inputs'!AA27))>'Model inputs'!AA24,IF(OR(IF(EXACT("30-van fleets","80-van fleets"),IF('Model inputs'!AA14="","",'Model inputs'!AA14),IF('Model inputs'!AA27="","",'Model inputs'!AA27))="",'Model inputs'!AA24=""),"",IF(EXACT("30-van fleets","80-van fleets"),IF('Model inputs'!AA14="","",'Model inputs'!AA14),IF('Model inputs'!AA27="","",'Model inputs'!AA27))>'Model inputs'!AA24))="",FALSE,IF(ISERROR(IF(EXACT("30-van fleets","80-van fleets"),IF('Model inputs'!AA14="","",'Model inputs'!AA14),IF('Model inputs'!AA27="","",'Model inputs'!AA27))>'Model inputs'!AA24),IF(EXACT("30-van fleets","80-van fleets"),IF('Model inputs'!AA14="","",'Model inputs'!AA14),IF('Model inputs'!AA27="","",'Model inputs'!AA27))>'Model inputs'!AA24,IF(OR(IF(EXACT("30-van fleets","80-van fleets"),IF('Model inputs'!AA14="","",'Model inputs'!AA14),IF('Model inputs'!AA27="","",'Model inputs'!AA27))="",'Model inputs'!AA24=""),"",IF(EXACT("30-van fleets","80-van fleets"),IF('Model inputs'!AA14="","",'Model inputs'!AA14),IF('Model inputs'!AA27="","",'Model inputs'!AA27))>'Model inputs'!AA24))),IF('Model inputs'!AA11="","",'Model inputs'!AA11),0)) -> 0 | P20: ='Fleet growth and revenue'!P9*IF(IF(IF(IF(ISERROR(IF(EXACT("30-van fleets","80-van fleets"),IF('Model inputs'!AA14="","",'Model inputs'!AA14),IF('Model inputs'!AA27="","",'Model inputs'!AA27))>'Model inputs'!AA24),IF(EXACT("30-van fleets","80-van fleets"),IF('Model inputs'!AA14="","",'Model inputs'!AA14),IF('Model inputs'!AA27="","",'Model inputs'!AA27))>'Model inputs'!AA24,IF(OR(IF(EXACT("30-van fleets","80-van fleets"),IF('Model inputs'!AA14="","",'Model inputs'!AA14),IF('Model inputs'!AA27="","",'Model inputs'!AA27))="",'Model inputs'!AA24=""),"",IF(EXACT("30-van fleets","80-van fleets"),IF('Model inputs'!AA14="","",'Model inputs'!AA14),IF('Model inputs'!AA27="","",'Model inputs'!AA27))>'Model inputs'!AA24))="",FALSE,IF(ISERROR(IF(EXACT("30-van fleets","80-van fleets"),IF('Model inputs'!AA14="","",'Model inputs'!AA14),IF('Model inputs'!AA27="","",'Model inputs'!AA27))>'Model inputs'!AA24),IF(EXACT("30-van fleets","80-van fleets"),IF('Model inputs'!AA14="","",'Model inputs'!AA14),IF('Model inputs'!AA27="","",'Model inputs'!AA27))>'Model inputs'!AA24,IF(OR(IF(EXACT("30-van fleets","80-van fleets"),IF('Model inputs'!AA14="","",'Model inputs'!AA14),IF('Model inputs'!AA27="","",'Model inputs'!AA27))="",'Model inputs'!AA24=""),"",IF(EXACT("30-van fleets","80-van fleets"),IF('Model inputs'!AA14="","",'Model inputs'!AA14),IF('Model inputs'!AA27="","",'Model inputs'!AA27))>'Model inputs'!AA24))),IF('Model inputs'!AA11="","",'Model inputs'!AA11),0)="",0,IF(IF(IF(ISERROR(IF(EXACT("30-van fleets","80-van fleets"),IF('Model inputs'!AA14="","",'Model inputs'!AA14),IF('Model inputs'!AA27="","",'Model inputs'!AA27))>'Model inputs'!AA24),IF(EXACT("30-van fleets","80-van fleets"),IF('Model inputs'!AA14="","",'Model inputs'!AA14),IF('Model inputs'!AA27="","",'Model inputs'!AA27))>'Model inputs'!AA24,IF(OR(IF(EXACT("30-van fleets","80-van fleets"),IF('Model inputs'!AA14="","",'Model inputs'!AA14),IF('Model inputs'!AA27="","",'Model inputs'!AA27))="",'Model inputs'!AA24=""),"",IF(EXACT("30-van fleets","80-van fleets"),IF('Model inputs'!AA14="","",'Model inputs'!AA14),IF('Model inputs'!AA27="","",'Model inputs'!AA27))>'Model inputs'!AA24))="",FALSE,IF(ISERROR(IF(EXACT("30-van fleets","80-van fleets"),IF('Model inputs'!AA14="","",'Model inputs'!AA14),IF('Model inputs'!AA27="","",'Model inputs'!AA27))>'Model inputs'!AA24),IF(EXACT("30-van fleets","80-van fleets"),IF('Model inputs'!AA14="","",'Model inputs'!AA14),IF('Model inputs'!AA27="","",'Model inputs'!AA27))>'Model inputs'!AA24,IF(OR(IF(EXACT("30-van fleets","80-van fleets"),IF('Model inputs'!AA14="","",'Model inputs'!AA14),IF('Model inputs'!AA27="","",'Model inputs'!AA27))="",'Model inputs'!AA24=""),"",IF(EXACT("30-van fleets","80-van fleets"),IF('Model inputs'!AA14="","",'Model inputs'!AA14),IF('Model inputs'!AA27="","",'Model inputs'!AA27))>'Model inputs'!AA24))),IF('Model inputs'!AA11="","",'Model inputs'!AA11),0)) -> 0 | Q20: ='Fleet growth and revenue'!Q9*IF(IF(IF(IF(ISERROR(IF(EXACT("30-van fleets","80-van fleets"),IF('Model inputs'!AA14="","",'Model inputs'!AA14),IF('Model inputs'!AA27="","",'Model inputs'!AA27))>'Model inputs'!AA24),IF(EXACT("30-van fleets","80-van fleets"),IF('Model inputs'!AA14="","",'Model inputs'!AA14),IF('Model inputs'!AA27="","",'Model inputs'!AA27))>'Model inputs'!AA24,IF(OR(IF(EXACT("30-van fleets","80-van fleets"),IF('Model inputs'!AA14="","",'Model inputs'!AA14),IF('Model inputs'!AA27="","",'Model inputs'!AA27))="",'Model inputs'!AA24=""),"",IF(EXACT("30-van fleets","80-van fleets"),IF('Model inputs'!AA14="","",'Model inputs'!AA14),IF('Model inputs'!AA27="","",'Model inputs'!AA27))>'Model inputs'!AA24))="",FALSE,IF(ISERROR(IF(EXACT("30-van fleets","80-van fleets"),IF('Model inputs'!AA14="","",'Model inputs'!AA14),IF('Model inputs'!AA27="","",'Model inputs'!AA27))>'Model inputs'!AA24),IF(EXACT("30-van fleets","80-van fleets"),IF('Model inputs'!AA14="","",'Model inputs'!AA14),IF('Model inputs'!AA27="","",'Model inputs'!AA27))>'Model inputs'!AA24,IF(OR(IF(EXACT("30-van fleets","80-van fleets"),IF('Model inputs'!AA14="","",'Model inputs'!AA14),IF('Model inputs'!AA27="","",'Model inputs'!AA27))="",'Model inputs'!AA24=""),"",IF(EXACT("30-van fleets","80-van fleets"),IF('Model inputs'!AA14="","",'Model inputs'!AA14),IF('Model inputs'!AA27="","",'Model inputs'!AA27))>'Model inputs'!AA24))),IF('Model inputs'!AA11="","",'Model inputs'!AA11),0)="",0,IF(IF(IF(ISERROR(IF(EXACT("30-van fleets","80-van fleets"),IF('Model inputs'!AA14="","",'Model inputs'!AA14),IF('Model inputs'!AA27="","",'Model inputs'!AA27))>'Model inputs'!AA24),IF(EXACT("30-van fleets","80-van fleets"),IF('Model inputs'!AA14="","",'Model inputs'!AA14),IF('Model inputs'!AA27="","",'Model inputs'!AA27))>'Model inputs'!AA24,IF(OR(IF(EXACT("30-van fleets","80-van fleets"),IF('Model inputs'!AA14="","",'Model inputs'!AA14),IF('Model inputs'!AA27="","",'Model inputs'!AA27))="",'Model inputs'!AA24=""),"",IF(EXACT("30-van fleets","80-van fleets"),IF('Model inputs'!AA14="","",'Model inputs'!AA14),IF('Model inputs'!AA27="","",'Model inputs'!AA27))>'Model inputs'!AA24))="",FALSE,IF(ISERROR(IF(EXACT("30-van fleets","80-van fleets"),IF('Model inputs'!AA14="","",'Model inputs'!AA14),IF('Model inputs'!AA27="","",'Model inputs'!AA27))>'Model inputs'!AA24),IF(EXACT("30-van fleets","80-van fleets"),IF('Model inputs'!AA14="","",'Model inputs'!AA14),IF('Model inputs'!AA27="","",'Model inputs'!AA27))>'Model inputs'!AA24,IF(OR(IF(EXACT("30-van fleets","80-van fleets"),IF('Model inputs'!AA14="","",'Model inputs'!AA14),IF('Model inputs'!AA27="","",'Model inputs'!AA27))="",'Model inputs'!AA24=""),"",IF(EXACT("30-van fleets","80-van fleets"),IF('Model inputs'!AA14="","",'Model inputs'!AA14),IF('Model inputs'!AA27="","",'Model inputs'!AA27))>'Model inputs'!AA24))),IF('Model inputs'!AA11="","",'Model inputs'!AA11),0)) -> 0 | R20: ='Fleet growth and revenue'!R9*IF(IF(IF(IF(ISERROR(IF(EXACT("30-van fleets","80-van fleets"),IF('Model inputs'!AA14="","",'Model inputs'!AA14),IF('Model inputs'!AA27="","",'Model inputs'!AA27))>'Model inputs'!AA24),IF(EXACT("30-van fleets","80-van fleets"),IF('Model inputs'!AA14="","",'Model inputs'!AA14),IF('Model inputs'!AA27="","",'Model inputs'!AA27))>'Model inputs'!AA24,IF(OR(IF(EXACT("30-van fleets","80-van fleets"),IF('Model inputs'!AA14="","",'Model inputs'!AA14),IF('Model inputs'!AA27="","",'Model inputs'!AA27))="",'Model inputs'!AA24=""),"",IF(EXACT("30-van fleets","80-van fleets"),IF('Model inputs'!AA14="","",'Model inputs'!AA14),IF('Model inputs'!AA27="","",'Model inputs'!AA27))>'Model inputs'!AA24))="",FALSE,IF(ISERROR(IF(EXACT("30-van fleets","80-van fleets"),IF('Model inputs'!AA14="","",'Model inputs'!AA14),IF('Model inputs'!AA27="","",'Model inputs'!AA27))>'Model inputs'!AA24),IF(EXACT("30-van fleets","80-van fleets"),IF('Model inputs'!AA14="","",'Model inputs'!AA14),IF('Model inputs'!AA27="","",'Model inputs'!AA27))>'Model inputs'!AA24,IF(OR(IF(EXACT("30-van fleets","80-van fleets"),IF('Model inputs'!AA14="","",'Model inputs'!AA14),IF('Model inputs'!AA27="","",'Model inputs'!AA27))="",'Model inputs'!AA24=""),"",IF(EXACT("30-van fleets","80-van fleets"),IF('Model inputs'!AA14="","",'Model inputs'!AA14),IF('Model inputs'!AA27="","",'Model inputs'!AA27))>'Model inputs'!AA24))),IF('Model inputs'!AA11="","",'Model inputs'!AA11),0)="",0,IF(IF(IF(ISERROR(IF(EXACT("30-van fleets","80-van fleets"),IF('Model inputs'!AA14="","",'Model inputs'!AA14),IF('Model inputs'!AA27="","",'Model inputs'!AA27))>'Model inputs'!AA24),IF(EXACT("30-van fleets","80-van fleets"),IF('Model inputs'!AA14="","",'Model inputs'!AA14),IF('Model inputs'!AA27="","",'Model inputs'!AA27))>'Model inputs'!AA24,IF(OR(IF(EXACT("30-van fleets","80-van fleets"),IF('Model inputs'!AA14="","",'Model inputs'!AA14),IF('Model inputs'!AA27="","",'Model inputs'!AA27))="",'Model inputs'!AA24=""),"",IF(EXACT("30-van fleets","80-van fleets"),IF('Model inputs'!AA14="","",'Model inputs'!AA14),IF('Model inputs'!AA27="","",'Model inputs'!AA27))>'Model inputs'!AA24))="",FALSE,IF(ISERROR(IF(EXACT("30-van fleets","80-van fleets"),IF('Model inputs'!AA14="","",'Model inputs'!AA14),IF('Model inputs'!AA27="","",'Model inputs'!AA27))>'Model inputs'!AA24),IF(EXACT("30-van fleets","80-van fleets"),IF('Model inputs'!AA14="","",'Model inputs'!AA14),IF('Model inputs'!AA27="","",'Model inputs'!AA27))>'Model inputs'!AA24,IF(OR(IF(EXACT("30-van fleets","80-van fleets"),IF('Model inputs'!AA14="","",'Model inputs'!AA14),IF('Model inputs'!AA27="","",'Model inputs'!AA27))="",'Model inputs'!AA24=""),"",IF(EXACT("30-van fleets","80-van fleets"),IF('Model inputs'!AA14="","",'Model inputs'!AA14),IF('Model inputs'!AA27="","",'Model inputs'!AA27))>'Model inputs'!AA24))),IF('Model inputs'!AA11="","",'Model inputs'!AA11),0)) -> 0 | S20: ='Fleet growth and revenue'!S9*IF(IF(IF(IF(ISERROR(IF(EXACT("30-van fleets","80-van fleets"),IF('Model inputs'!AA14="","",'Model inputs'!AA14),IF('Model inputs'!AA27="","",'Model inputs'!AA27))>'Model inputs'!AA24),IF(EXACT("30-van fleets","80-van fleets"),IF('Model inputs'!AA14="","",'Model inputs'!AA14),IF('Model inputs'!AA27="","",'Model inputs'!AA27))>'Model inputs'!AA24,IF(OR(IF(EXACT("30-van fleets","80-van fleets"),IF('Model inputs'!AA14="","",'Model inputs'!AA14),IF('Model inputs'!AA27="","",'Model inputs'!AA27))="",'Model inputs'!AA24=""),"",IF(EXACT("30-van fleets","80-van fleets"),IF('Model inputs'!AA14="","",'Model inputs'!AA14),IF('Model inputs'!AA27="","",'Model inputs'!AA27))>'Model inputs'!AA24))="",FALSE,IF(ISERROR(IF(EXACT("30-van fleets","80-van fleets"),IF('Model inputs'!AA14="","",'Model inputs'!AA14),IF('Model inputs'!AA27="","",'Model inputs'!AA27))>'Model inputs'!AA24),IF(EXACT("30-van fleets","80-van fleets"),IF('Model inputs'!AA14="","",'Model inputs'!AA14),IF('Model inputs'!AA27="","",'Model inputs'!AA27))>'Model inputs'!AA24,IF(OR(IF(EXACT("30-van fleets","80-van fleets"),IF('Model inputs'!AA14="","",'Model inputs'!AA14),IF('Model inputs'!AA27="","",'Model inputs'!AA27))="",'Model inputs'!AA24=""),"",IF(EXACT("30-van fleets","80-van fleets"),IF('Model inputs'!AA14="","",'Model inputs'!AA14),IF('Model inputs'!AA27="","",'Model inputs'!AA27))>'Model inputs'!AA24))),IF('Model inputs'!AA11="","",'Model inputs'!AA11),0)="",0,IF(IF(IF(ISERROR(IF(EXACT("30-van fleets","80-van fleets"),IF('Model inputs'!AA14="","",'Model inputs'!AA14),IF('Model inputs'!AA27="","",'Model inputs'!AA27))>'Model inputs'!AA24),IF(EXACT("30-van fleets","80-van fleets"),IF('Model inputs'!AA14="","",'Model inputs'!AA14),IF('Model inputs'!AA27="","",'Model inputs'!AA27))>'Model inputs'!AA24,IF(OR(IF(EXACT("30-van fleets","80-van fleets"),IF('Model inputs'!AA14="","",'Model inputs'!AA14),IF('Model inputs'!AA27="","",'Model inputs'!AA27))="",'Model inputs'!AA24=""),"",IF(EXACT("30-van fleets","80-van fleets"),IF('Model inputs'!AA14="","",'Model inputs'!AA14),IF('Model inputs'!AA27="","",'Model inputs'!AA27))>'Model inputs'!AA24))="",FALSE,IF(ISERROR(IF(EXACT("30-van fleets","80-van fleets"),IF('Model inputs'!AA14="","",'Model inputs'!AA14),IF('Model inputs'!AA27="","",'Model inputs'!AA27))>'Model inputs'!AA24),IF(EXACT("30-van fleets","80-van fleets"),IF('Model inputs'!AA14="","",'Model inputs'!AA14),IF('Model inputs'!AA27="","",'Model inputs'!AA27))>'Model inputs'!AA24,IF(OR(IF(EXACT("30-van fleets","80-van fleets"),IF('Model inputs'!AA14="","",'Model inputs'!AA14),IF('Model inputs'!AA27="","",'Model inputs'!AA27))="",'Model inputs'!AA24=""),"",IF(EXACT("30-van fleets","80-van fleets"),IF('Model inputs'!AA14="","",'Model inputs'!AA14),IF('Model inputs'!AA27="","",'Model inputs'!AA27))>'Model inputs'!AA24))),IF('Model inputs'!AA11="","",'Model inputs'!AA11),0)) -> 0 | T20: ='Fleet growth and revenue'!T9*IF(IF(IF(IF(ISERROR(IF(EXACT("30-van fleets","80-van fleets"),IF('Model inputs'!AA14="","",'Model inputs'!AA14),IF('Model inputs'!AA27="","",'Model inputs'!AA27))>'Model inputs'!AA24),IF(EXACT("30-van fleets","80-van fleets"),IF('Model inputs'!AA14="","",'Model inputs'!AA14),IF('Model inputs'!AA27="","",'Model inputs'!AA27))>'Model inputs'!AA24,IF(OR(IF(EXACT("30-van fleets","80-van fleets"),IF('Model inputs'!AA14="","",'Model inputs'!AA14),IF('Model inputs'!AA27="","",'Model inputs'!AA27))="",'Model inputs'!AA24=""),"",IF(EXACT("30-van fleets","80-van fleets"),IF('Model inputs'!AA14="","",'Model inputs'!AA14),IF('Model inputs'!AA27="","",'Model inputs'!AA27))>'Model inputs'!AA24))="",FALSE,IF(ISERROR(IF(EXACT("30-van fleets","80-van fleets"),IF('Model inputs'!AA14="","",'Model inputs'!AA14),IF('Model inputs'!AA27="","",'Model inputs'!AA27))>'Model inputs'!AA24),IF(EXACT("30-van fleets","80-van fleets"),IF('Model inputs'!AA14="","",'Model inputs'!AA14),IF('Model inputs'!AA27="","",'Model inputs'!AA27))>'Model inputs'!AA24,IF(OR(IF(EXACT("30-van fleets","80-van fleets"),IF('Model inputs'!AA14="","",'Model inputs'!AA14),IF('Model inputs'!AA27="","",'Model inputs'!AA27))="",'Model inputs'!AA24=""),"",IF(EXACT("30-van fleets","80-van fleets"),IF('Model inputs'!AA14="","",'Model inputs'!AA14),IF('Model inputs'!AA27="","",'Model inputs'!AA27))>'Model inputs'!AA24))),IF('Model inputs'!AA11="","",'Model inputs'!AA11),0)="",0,IF(IF(IF(ISERROR(IF(EXACT("30-van fleets","80-van fleets"),IF('Model inputs'!AA14="","",'Model inputs'!AA14),IF('Model inputs'!AA27="","",'Model inputs'!AA27))>'Model inputs'!AA24),IF(EXACT("30-van fleets","80-van fleets"),IF('Model inputs'!AA14="","",'Model inputs'!AA14),IF('Model inputs'!AA27="","",'Model inputs'!AA27))>'Model inputs'!AA24,IF(OR(IF(EXACT("30-van fleets","80-van fleets"),IF('Model inputs'!AA14="","",'Model inputs'!AA14),IF('Model inputs'!AA27="","",'Model inputs'!AA27))="",'Model inputs'!AA24=""),"",IF(EXACT("30-van fleets","80-van fleets"),IF('Model inputs'!AA14="","",'Model inputs'!AA14),IF('Model inputs'!AA27="","",'Model inputs'!AA27))>'Model inputs'!AA24))="",FALSE,IF(ISERROR(IF(EXACT("30-van fleets","80-van fleets"),IF('Model inputs'!AA14="","",'Model inputs'!AA14),IF('Model inputs'!AA27="","",'Model inputs'!AA27))>'Model inputs'!AA24),IF(EXACT("30-van fleets","80-van fleets"),IF('Model inputs'!AA14="","",'Model inputs'!AA14),IF('Model inputs'!AA27="","",'Model inputs'!AA27))>'Model inputs'!AA24,IF(OR(IF(EXACT("30-van fleets","80-van fleets"),IF('Model inputs'!AA14="","",'Model inputs'!AA14),IF('Model inputs'!AA27="","",'Model inputs'!AA27))="",'Model inputs'!AA24=""),"",IF(EXACT("30-van fleets","80-van fleets"),IF('Model inputs'!AA14="","",'Model inputs'!AA14),IF('Model inputs'!AA27="","",'Model inputs'!AA27))>'Model inputs'!AA24))),IF('Model inputs'!AA11="","",'Model inputs'!AA11),0)) -> 0 | U20: ='Fleet growth and revenue'!U9*IF(IF(IF(IF(ISERROR(IF(EXACT("30-van fleets","80-van fleets"),IF('Model inputs'!AA14="","",'Model inputs'!AA14),IF('Model inputs'!AA27="","",'Model inputs'!AA27))>'Model inputs'!AA24),IF(EXACT("30-van fleets","80-van fleets"),IF('Model inputs'!AA14="","",'Model inputs'!AA14),IF('Model inputs'!AA27="","",'Model inputs'!AA27))>'Model inputs'!AA24,IF(OR(IF(EXACT("30-van fleets","80-van fleets"),IF('Model inputs'!AA14="","",'Model inputs'!AA14),IF('Model inputs'!AA27="","",'Model inputs'!AA27))="",'Model inputs'!AA24=""),"",IF(EXACT("30-van fleets","80-van fleets"),IF('Model inputs'!AA14="","",'Model inputs'!AA14),IF('Model inputs'!AA27="","",'Model inputs'!AA27))>'Model inputs'!AA24))="",FALSE,IF(ISERROR(IF(EXACT("30-van fleets","80-van fleets"),IF('Model inputs'!AA14="","",'Model inputs'!AA14),IF('Model inputs'!AA27="","",'Model inputs'!AA27))>'Model inputs'!AA24),IF(EXACT("30-van fleets","80-van fleets"),IF('Model inputs'!AA14="","",'Model inputs'!AA14),IF('Model inputs'!AA27="","",'Model inputs'!AA27))>'Model inputs'!AA24,IF(OR(IF(EXACT("30-van fleets","80-van fleets"),IF('Model inputs'!AA14="","",'Model inputs'!AA14),IF('Model inputs'!AA27="","",'Model inputs'!AA27))="",'Model inputs'!AA24=""),"",IF(EXACT("30-van fleets","80-van fleets"),IF('Model inputs'!AA14="","",'Model inputs'!AA14),IF('Model inputs'!AA27="","",'Model inputs'!AA27))>'Model inputs'!AA24))),IF('Model inputs'!AA11="","",'Model inputs'!AA11),0)="",0,IF(IF(IF(ISERROR(IF(EXACT("30-van fleets","80-van fleets"),IF('Model inputs'!AA14="","",'Model inputs'!AA14),IF('Model inputs'!AA27="","",'Model inputs'!AA27))>'Model inputs'!AA24),IF(EXACT("30-van fleets","80-van fleets"),IF('Model inputs'!AA14="","",'Model inputs'!AA14),IF('Model inputs'!AA27="","",'Model inputs'!AA27))>'Model inputs'!AA24,IF(OR(IF(EXACT("30-van fleets","80-van fleets"),IF('Model inputs'!AA14="","",'Model inputs'!AA14),IF('Model inputs'!AA27="","",'Model inputs'!AA27))="",'Model inputs'!AA24=""),"",IF(EXACT("30-van fleets","80-van fleets"),IF('Model inputs'!AA14="","",'Model inputs'!AA14),IF('Model inputs'!AA27="","",'Model inputs'!AA27))>'Model inputs'!AA24))="",FALSE,IF(ISERROR(IF(EXACT("30-van fleets","80-van fleets"),IF('Model inputs'!AA14="","",'Model inputs'!AA14),IF('Model inputs'!AA27="","",'Model inputs'!AA27))>'Model inputs'!AA24),IF(EXACT("30-van fleets","80-van fleets"),IF('Model inputs'!AA14="","",'Model inputs'!AA14),IF('Model inputs'!AA27="","",'Model inputs'!AA27))>'Model inputs'!AA24,IF(OR(IF(EXACT("30-van fleets","80-van fleets"),IF('Model inputs'!AA14="","",'Model inputs'!AA14),IF('Model inputs'!AA27="","",'Model inputs'!AA27))="",'Model inputs'!AA24=""),"",IF(EXACT("30-van fleets","80-van fleets"),IF('Model inputs'!AA14="","",'Model inputs'!AA14),IF('Model inputs'!AA27="","",'Model inputs'!AA27))>'Model inputs'!AA24))),IF('Model inputs'!AA11="","",'Model inputs'!AA11),0)) -> 0 | V20: ='Fleet growth and revenue'!V9*IF(IF(IF(IF(ISERROR(IF(EXACT("30-van fleets","80-van fleets"),IF('Model inputs'!AA14="","",'Model inputs'!AA14),IF('Model inputs'!AA27="","",'Model inputs'!AA27))>'Model inputs'!AA24),IF(EXACT("30-van fleets","80-van fleets"),IF('Model inputs'!AA14="","",'Model inputs'!AA14),IF('Model inputs'!AA27="","",'Model inputs'!AA27))>'Model inputs'!AA24,IF(OR(IF(EXACT("30-van fleets","80-van fleets"),IF('Model inputs'!AA14="","",'Model inputs'!AA14),IF('Model inputs'!AA27="","",'Model inputs'!AA27))="",'Model inputs'!AA24=""),"",IF(EXACT("30-van fleets","80-van fleets"),IF('Model inputs'!AA14="","",'Model inputs'!AA14),IF('Model inputs'!AA27="","",'Model inputs'!AA27))>'Model inputs'!AA24))="",FALSE,IF(ISERROR(IF(EXACT("30-van fleets","80-van fleets"),IF('Model inputs'!AA14="","",'Model inputs'!AA14),IF('Model inputs'!AA27="","",'Model inputs'!AA27))>'Model inputs'!AA24),IF(EXACT("30-van fleets","80-van fleets"),IF('Model inputs'!AA14="","",'Model inputs'!AA14),IF('Model inputs'!AA27="","",'Model inputs'!AA27))>'Model inputs'!AA24,IF(OR(IF(EXACT("30-van fleets","80-van fleets"),IF('Model inputs'!AA14="","",'Model inputs'!AA14),IF('Model inputs'!AA27="","",'Model inputs'!AA27))="",'Model inputs'!AA24=""),"",IF(EXACT("30-van fleets","80-van fleets"),IF('Model inputs'!AA14="","",'Model inputs'!AA14),IF('Model inputs'!AA27="","",'Model inputs'!AA27))>'Model inputs'!AA24))),IF('Model inputs'!AA11="","",'Model inputs'!AA11),0)="",0,IF(IF(IF(ISERROR(IF(EXACT("30-van fleets","80-van fleets"),IF('Model inputs'!AA14="","",'Model inputs'!AA14),IF('Model inputs'!AA27="","",'Model inputs'!AA27))>'Model inputs'!AA24),IF(EXACT("30-van fleets","80-van fleets"),IF('Model inputs'!AA14="","",'Model inputs'!AA14),IF('Model inputs'!AA27="","",'Model inputs'!AA27))>'Model inputs'!AA24,IF(OR(IF(EXACT("30-van fleets","80-van fleets"),IF('Model inputs'!AA14="","",'Model inputs'!AA14),IF('Model inputs'!AA27="","",'Model inputs'!AA27))="",'Model inputs'!AA24=""),"",IF(EXACT("30-van fleets","80-van fleets"),IF('Model inputs'!AA14="","",'Model inputs'!AA14),IF('Model inputs'!AA27="","",'Model inputs'!AA27))>'Model inputs'!AA24))="",FALSE,IF(ISERROR(IF(EXACT("30-van fleets","80-van fleets"),IF('Model inputs'!AA14="","",'Model inputs'!AA14),IF('Model inputs'!AA27="","",'Model inputs'!AA27))>'Model inputs'!AA24),IF(EXACT("30-van fleets","80-van fleets"),IF('Model inputs'!AA14="","",'Model inputs'!AA14),IF('Model inputs'!AA27="","",'Model inputs'!AA27))>'Model inputs'!AA24,IF(OR(IF(EXACT("30-van fleets","80-van fleets"),IF('Model inputs'!AA14="","",'Model inputs'!AA14),IF('Model inputs'!AA27="","",'Model inputs'!AA27))="",'Model inputs'!AA24=""),"",IF(EXACT("30-van fleets","80-van fleets"),IF('Model inputs'!AA14="","",'Model inputs'!AA14),IF('Model inputs'!AA27="","",'Model inputs'!AA27))>'Model inputs'!AA24))),IF('Model inputs'!AA11="","",'Model inputs'!AA11),0)) -> 0 | W20: ='Fleet growth and revenue'!W9*IF(IF(IF(IF(ISERROR(IF(EXACT("30-van fleets","80-van fleets"),IF('Model inputs'!AA14="","",'Model inputs'!AA14),IF('Model inputs'!AA27="","",'Model inputs'!AA27))>'Model inputs'!AA24),IF(EXACT("30-van fleets","80-van fleets"),IF('Model inputs'!AA14="","",'Model inputs'!AA14),IF('Model inputs'!AA27="","",'Model inputs'!AA27))>'Model inputs'!AA24,IF(OR(IF(EXACT("30-van fleets","80-van fleets"),IF('Model inputs'!AA14="","",'Model inputs'!AA14),IF('Model inputs'!AA27="","",'Model inputs'!AA27))="",'Model inputs'!AA24=""),"",IF(EXACT("30-van fleets","80-van fleets"),IF('Model inputs'!AA14="","",'Model inputs'!AA14),IF('Model inputs'!AA27="","",'Model inputs'!AA27))>'Model inputs'!AA24))="",FALSE,IF(ISERROR(IF(EXACT("30-van fleets","80-van fleets"),IF('Model inputs'!AA14="","",'Model inputs'!AA14),IF('Model inputs'!AA27="","",'Model inputs'!AA27))>'Model inputs'!AA24),IF(EXACT("30-van fleets","80-van fleets"),IF('Model inputs'!AA14="","",'Model inputs'!AA14),IF('Model inputs'!AA27="","",'Model inputs'!AA27))>'Model inputs'!AA24,IF(OR(IF(EXACT("30-van fleets","80-van fleets"),IF('Model inputs'!AA14="","",'Model inputs'!AA14),IF('Model inputs'!AA27="","",'Model inputs'!AA27))="",'Model inputs'!AA24=""),"",IF(EXACT("30-van fleets","80-van fleets"),IF('Model inputs'!AA14="","",'Model inputs'!AA14),IF('Model inputs'!AA27="","",'Model inputs'!AA27))>'Model inputs'!AA24))),IF('Model inputs'!AA11="","",'Model inputs'!AA11),0)="",0,IF(IF(IF(ISERROR(IF(EXACT("30-van fleets","80-van fleets"),IF('Model inputs'!AA14="","",'Model inputs'!AA14),IF('Model inputs'!AA27="","",'Model inputs'!AA27))>'Model inputs'!AA24),IF(EXACT("30-van fleets","80-van fleets"),IF('Model inputs'!AA14="","",'Model inputs'!AA14),IF('Model inputs'!AA27="","",'Model inputs'!AA27))>'Model inputs'!AA24,IF(OR(IF(EXACT("30-van fleets","80-van fleets"),IF('Model inputs'!AA14="","",'Model inputs'!AA14),IF('Model inputs'!AA27="","",'Model inputs'!AA27))="",'Model inputs'!AA24=""),"",IF(EXACT("30-van fleets","80-van fleets"),IF('Model inputs'!AA14="","",'Model inputs'!AA14),IF('Model inputs'!AA27="","",'Model inputs'!AA27))>'Model inputs'!AA24))="",FALSE,IF(ISERROR(IF(EXACT("30-van fleets","80-van fleets"),IF('Model inputs'!AA14="","",'Model inputs'!AA14),IF('Model inputs'!AA27="","",'Model inputs'!AA27))>'Model inputs'!AA24),IF(EXACT("30-van fleets","80-van fleets"),IF('Model inputs'!AA14="","",'Model inputs'!AA14),IF('Model inputs'!AA27="","",'Model inputs'!AA27))>'Model inputs'!AA24,IF(OR(IF(EXACT("30-van fleets","80-van fleets"),IF('Model inputs'!AA14="","",'Model inputs'!AA14),IF('Model inputs'!AA27="","",'Model inputs'!AA27))="",'Model inputs'!AA24=""),"",IF(EXACT("30-van fleets","80-van fleets"),IF('Model inputs'!AA14="","",'Model inputs'!AA14),IF('Model inputs'!AA27="","",'Model inputs'!AA27))>'Model inputs'!AA24))),IF('Model inputs'!AA11="","",'Model inputs'!AA11),0)) -> 0 | X20: ='Fleet growth and revenue'!X9*IF(IF(IF(IF(ISERROR(IF(EXACT("30-van fleets","80-van fleets"),IF('Model inputs'!AA14="","",'Model inputs'!AA14),IF('Model inputs'!AA27="","",'Model inputs'!AA27))>'Model inputs'!AA24),IF(EXACT("30-van fleets","80-van fleets"),IF('Model inputs'!AA14="","",'Model inputs'!AA14),IF('Model inputs'!AA27="","",'Model inputs'!AA27))>'Model inputs'!AA24,IF(OR(IF(EXACT("30-van fleets","80-van fleets"),IF('Model inputs'!AA14="","",'Model inputs'!AA14),IF('Model inputs'!AA27="","",'Model inputs'!AA27))="",'Model inputs'!AA24=""),"",IF(EXACT("30-van fleets","80-van fleets"),IF('Model inputs'!AA14="","",'Model inputs'!AA14),IF('Model inputs'!AA27="","",'Model inputs'!AA27))>'Model inputs'!AA24))="",FALSE,IF(ISERROR(IF(EXACT("30-van fleets","80-van fleets"),IF('Model inputs'!AA14="","",'Model inputs'!AA14),IF('Model inputs'!AA27="","",'Model inputs'!AA27))>'Model inputs'!AA24),IF(EXACT("30-van fleets","80-van fleets"),IF('Model inputs'!AA14="","",'Model inputs'!AA14),IF('Model inputs'!AA27="","",'Model inputs'!AA27))>'Model inputs'!AA24,IF(OR(IF(EXACT("30-van fleets","80-van fleets"),IF('Model inputs'!AA14="","",'Model inputs'!AA14),IF('Model inputs'!AA27="","",'Model inputs'!AA27))="",'Model inputs'!AA24=""),"",IF(EXACT("30-van fleets","80-van fleets"),IF('Model inputs'!AA14="","",'Model inputs'!AA14),IF('Model inputs'!AA27="","",'Model inputs'!AA27))>'Model inputs'!AA24))),IF('Model inputs'!AA11="","",'Model inputs'!AA11),0)="",0,IF(IF(IF(ISERROR(IF(EXACT("30-van fleets","80-van fleets"),IF('Model inputs'!AA14="","",'Model inputs'!AA14),IF('Model inputs'!AA27="","",'Model inputs'!AA27))>'Model inputs'!AA24),IF(EXACT("30-van fleets","80-van fleets"),IF('Model inputs'!AA14="","",'Model inputs'!AA14),IF('Model inputs'!AA27="","",'Model inputs'!AA27))>'Model inputs'!AA24,IF(OR(IF(EXACT("30-van fleets","80-van fleets"),IF('Model inputs'!AA14="","",'Model inputs'!AA14),IF('Model inputs'!AA27="","",'Model inputs'!AA27))="",'Model inputs'!AA24=""),"",IF(EXACT("30-van fleets","80-van fleets"),IF('Model inputs'!AA14="","",'Model inputs'!AA14),IF('Model inputs'!AA27="","",'Model inputs'!AA27))>'Model inputs'!AA24))="",FALSE,IF(ISERROR(IF(EXACT("30-van fleets","80-van fleets"),IF('Model inputs'!AA14="","",'Model inputs'!AA14),IF('Model inputs'!AA27="","",'Model inputs'!AA27))>'Model inputs'!AA24),IF(EXACT("30-van fleets","80-van fleets"),IF('Model inputs'!AA14="","",'Model inputs'!AA14),IF('Model inputs'!AA27="","",'Model inputs'!AA27))>'Model inputs'!AA24,IF(OR(IF(EXACT("30-van fleets","80-van fleets"),IF('Model inputs'!AA14="","",'Model inputs'!AA14),IF('Model inputs'!AA27="","",'Model inputs'!AA27))="",'Model inputs'!AA24=""),"",IF(EXACT("30-van fleets","80-van fleets"),IF('Model inputs'!AA14="","",'Model inputs'!AA14),IF('Model inputs'!AA27="","",'Model inputs'!AA27))>'Model inputs'!AA24))),IF('Model inputs'!AA11="","",'Model inputs'!AA11),0)) -> 0 | Y20: ='Fleet growth and revenue'!Y9*IF(IF(IF(IF(ISERROR(IF(EXACT("30-van fleets","80-van fleets"),IF('Model inputs'!AA14="","",'Model inputs'!AA14),IF('Model inputs'!AA27="","",'Model inputs'!AA27))>'Model inputs'!AA24),IF(EXACT("30-van fleets","80-van fleets"),IF('Model inputs'!AA14="","",'Model inputs'!AA14),IF('Model inputs'!AA27="","",'Model inputs'!AA27))>'Model inputs'!AA24,IF(OR(IF(EXACT("30-van fleets","80-van fleets"),IF('Model inputs'!AA14="","",'Model inputs'!AA14),IF('Model inputs'!AA27="","",'Model inputs'!AA27))="",'Model inputs'!AA24=""),"",IF(EXACT("30-van fleets","80-van fleets"),IF('Model inputs'!AA14="","",'Model inputs'!AA14),IF('Model inputs'!AA27="","",'Model inputs'!AA27))>'Model inputs'!AA24))="",FALSE,IF(ISERROR(IF(EXACT("30-van fleets","80-van fleets"),IF('Model inputs'!AA14="","",'Model inputs'!AA14),IF('Model inputs'!AA27="","",'Model inputs'!AA27))>'Model inputs'!AA24),IF(EXACT("30-van fleets","80-van fleets"),IF('Model inputs'!AA14="","",'Model inputs'!AA14),IF('Model inputs'!AA27="","",'Model inputs'!AA27))>'Model inputs'!AA24,IF(OR(IF(EXACT("30-van fleets","80-van fleets"),IF('Model inputs'!AA14="","",'Model inputs'!AA14),IF('Model inputs'!AA27="","",'Model inputs'!AA27))="",'Model inputs'!AA24=""),"",IF(EXACT("30-van fleets","80-van fleets"),IF('Model inputs'!AA14="","",'Model inputs'!AA14),IF('Model inputs'!AA27="","",'Model inputs'!AA27))>'Model inputs'!AA24))),IF('Model inputs'!AA11="","",'Model inputs'!AA11),0)="",0,IF(IF(IF(ISERROR(IF(EXACT("30-van fleets","80-van fleets"),IF('Model inputs'!AA14="","",'Model inputs'!AA14),IF('Model inputs'!AA27="","",'Model inputs'!AA27))>'Model inputs'!AA24),IF(EXACT("30-van fleets","80-van fleets"),IF('Model inputs'!AA14="","",'Model inputs'!AA14),IF('Model inputs'!AA27="","",'Model inputs'!AA27))>'Model inputs'!AA24,IF(OR(IF(EXACT("30-van fleets","80-van fleets"),IF('Model inputs'!AA14="","",'Model inputs'!AA14),IF('Model inputs'!AA27="","",'Model inputs'!AA27))="",'Model inputs'!AA24=""),"",IF(EXACT("30-van fleets","80-van fleets"),IF('Model inputs'!AA14="","",'Model inputs'!AA14),IF('Model inputs'!AA27="","",'Model inputs'!AA27))>'Model inputs'!AA24))="",FALSE,IF(ISERROR(IF(EXACT("30-van fleets","80-van fleets"),IF('Model inputs'!AA14="","",'Model inputs'!AA14),IF('Model inputs'!AA27="","",'Model inputs'!AA27))>'Model inputs'!AA24),IF(EXACT("30-van fleets","80-van fleets"),IF('Model inputs'!AA14="","",'Model inputs'!AA14),IF('Model inputs'!AA27="","",'Model inputs'!AA27))>'Model inputs'!AA24,IF(OR(IF(EXACT("30-van fleets","80-van fleets"),IF('Model inputs'!AA14="","",'Model inputs'!AA14),IF('Model inputs'!AA27="","",'Model inputs'!AA27))="",'Model inputs'!AA24=""),"",IF(EXACT("30-van fleets","80-van fleets"),IF('Model inputs'!AA14="","",'Model inputs'!AA14),IF('Model inputs'!AA27="","",'Model inputs'!AA27))>'Model inputs'!AA24))),IF('Model inputs'!AA11="","",'Model inputs'!AA11),0)) -> 0
